[ {
  "uid" : "29889",
  "licenseId" : "24041996000",
  "country" : "BEL",
  "name" : {
    "firstName" : "Steven",
    "lastName" : "ABRAHAMS",
    "fullName" : "ABRAHAMS, Steven"
  },
  "gender" : "MALE",
  "hand" : "RIGHT",
  "birthDay" : {
    "y" : 1996,
    "m" : 4,
    "d" : 24
  }
}, {
  "uid" : "29888",
  "licenseId" : "19031995003",
  "country" : "BEL",
  "name" : {
    "firstName" : "Floris",
    "lastName" : "ABRAMS",
    "fullName" : "ABRAMS, Floris"
  },
  "gender" : "MALE",
  "hand" : "RIGHT",
  "birthDay" : {
    "y" : 1995,
    "m" : 3,
    "d" : 19
  }
}, {
  "uid" : "28370",
  "licenseId" : "19031995002",
  "country" : "BEL",
  "name" : {
    "firstName" : "Jolien",
    "lastName" : "ABRAMS",
    "fullName" : "ABRAMS, Jolien"
  },
  "gender" : "FEMALE",
  "hand" : "RIGHT",
  "birthDay" : {
    "y" : 1995,
    "m" : 3,
    "d" : 19
  }
}, {
  "uid" : "19685",
  "licenseId" : "27071989004",
  "country" : "BEL",
  "name" : {
    "firstName" : "Eli",
    "lastName" : "ANTHEUNIS",
    "fullName" : "ANTHEUNIS, Eli"
  },
  "gender" : "MALE",
  "hand" : "LEFT",
  "birthDay" : {
    "y" : 1989,
    "m" : 7,
    "d" : 27
  }
}, {
  "uid" : "1718",
  "licenseId" : "16031976000",
  "country" : "BEL",
  "name" : {
    "firstName" : "Olivier",
    "lastName" : "ANTONIS",
    "fullName" : "ANTONIS, Olivier"
  },
  "gender" : "MALE",
  "hand" : "RIGHT",
  "birthDay" : {
    "y" : 1976,
    "m" : 3,
    "d" : 16
  }
}, {
  "uid" : "18000",
  "licenseId" : "15071991000",
  "country" : "BEL",
  "name" : {
    "firstName" : "Sarah",
    "lastName" : "ARENS",
    "fullName" : "ARENS, Sarah"
  },
  "gender" : "FEMALE",
  "hand" : "RIGHT",
  "birthDay" : {
    "y" : 1991,
    "m" : 7,
    "d" : 15
  }
}, {
  "uid" : "33474",
  "licenseId" : "29041958000",
  "country" : "BEL",
  "name" : {
    "firstName" : "Christophe",
    "lastName" : "ARTS",
    "fullName" : "ARTS, Christophe"
  },
  "gender" : "MALE",
  "hand" : "RIGHT",
  "birthDay" : {
    "y" : 1958,
    "m" : 4,
    "d" : 29
  }
}, {
  "uid" : "32780",
  "licenseId" : null,
  "country" : "BEL",
  "name" : {
    "firstName" : "Arnaud",
    "lastName" : "AVAERT",
    "fullName" : "AVAERT, Arnaud"
  },
  "gender" : null,
  "hand" : null,
  "birthDay" : {
    "y" : 1980,
    "m" : 1,
    "d" : 11
  }
}, {
  "uid" : "19722",
  "licenseId" : "11121958000",
  "country" : "BEL",
  "name" : {
    "firstName" : "Dirk",
    "lastName" : "BAARENDSE",
    "fullName" : "BAARENDSE, Dirk"
  },
  "gender" : "MALE",
  "hand" : "RIGHT",
  "birthDay" : {
    "y" : 1958,
    "m" : 12,
    "d" : 11
  }
}, {
  "uid" : "19721",
  "licenseId" : "31031989003",
  "country" : "BEL",
  "name" : {
    "firstName" : "Tatiana",
    "lastName" : "BAARENDSE",
    "fullName" : "BAARENDSE, Tatiana"
  },
  "gender" : "FEMALE",
  "hand" : "RIGHT",
  "birthDay" : {
    "y" : 1989,
    "m" : 3,
    "d" : 31
  }
}, {
  "uid" : "31933",
  "licenseId" : "15101994003",
  "country" : "BEL",
  "name" : {
    "firstName" : "Maxime",
    "lastName" : "BAEKELANDT",
    "fullName" : "BAEKELANDT, Maxime"
  },
  "gender" : "MALE",
  "hand" : "RIGHT",
  "birthDay" : {
    "y" : 1994,
    "m" : 10,
    "d" : 15
  }
}, {
  "uid" : "34254",
  "licenseId" : "26071997002",
  "country" : "BEL",
  "name" : {
    "firstName" : "Arthur",
    "lastName" : "BAETENS",
    "fullName" : "BAETENS, Arthur"
  },
  "gender" : "MALE",
  "hand" : "RIGHT",
  "birthDay" : {
    "y" : 1997,
    "m" : 7,
    "d" : 26
  }
}, {
  "uid" : "29924",
  "licenseId" : "25021994004",
  "country" : "BEL",
  "name" : {
    "firstName" : "Julian",
    "lastName" : "BELLEMANS",
    "fullName" : "BELLEMANS, Julian"
  },
  "gender" : "MALE",
  "hand" : "RIGHT",
  "birthDay" : {
    "y" : 1994,
    "m" : 2,
    "d" : 25
  }
}, {
  "uid" : "42962",
  "licenseId" : null,
  "country" : "BEL",
  "name" : {
    "firstName" : "Florian",
    "lastName" : "BERNARD",
    "fullName" : "BERNARD, Florian"
  },
  "gender" : null,
  "hand" : null,
  "birthDay" : {
    "y" : 1991,
    "m" : 1,
    "d" : 25
  }
}, {
  "uid" : "12630",
  "licenseId" : "20041982004",
  "country" : "BEL",
  "name" : {
    "firstName" : "Frederic",
    "lastName" : "BICKELL",
    "fullName" : "BICKELL, Frederic"
  },
  "gender" : "MALE",
  "hand" : "RIGHT",
  "birthDay" : {
    "y" : 1982,
    "m" : 4,
    "d" : 20
  }
}, {
  "uid" : "1720",
  "licenseId" : "24071988000",
  "country" : "BEL",
  "name" : {
    "firstName" : "Gauthier",
    "lastName" : "BIELEN",
    "fullName" : "BIELEN, Gauthier"
  },
  "gender" : "MALE",
  "hand" : "RIGHT",
  "birthDay" : {
    "y" : 1988,
    "m" : 7,
    "d" : 24
  }
}, {
  "uid" : "12233",
  "licenseId" : "21111987000",
  "country" : "BEL",
  "name" : {
    "firstName" : "Evert",
    "lastName" : "BLEUS",
    "fullName" : "BLEUS, Evert"
  },
  "gender" : "MALE",
  "hand" : "LEFT",
  "birthDay" : {
    "y" : 1987,
    "m" : 11,
    "d" : 21
  }
}, {
  "uid" : "1722",
  "licenseId" : "01011986000",
  "country" : "BEL",
  "name" : {
    "firstName" : "Isaie",
    "lastName" : "BLOCH",
    "fullName" : "BLOCH, Isaie"
  },
  "gender" : "MALE",
  "hand" : "RIGHT",
  "birthDay" : {
    "y" : 1986,
    "m" : 1,
    "d" : 1
  }
}, {
  "uid" : "31691",
  "licenseId" : "23011998000",
  "country" : "BEL",
  "name" : {
    "firstName" : "Felix",
    "lastName" : "BLOMMAERT",
    "fullName" : "BLOMMAERT, Felix"
  },
  "gender" : "MALE",
  "hand" : "RIGHT",
  "birthDay" : {
    "y" : 1998,
    "m" : 1,
    "d" : 23
  }
}, {
  "uid" : "25813",
  "licenseId" : "06121993000",
  "country" : "BEL",
  "name" : {
    "firstName" : "Vivien",
    "lastName" : "BOGAERT",
    "fullName" : "BOGAERT, Vivien"
  },
  "gender" : "MALE",
  "hand" : "RIGHT",
  "birthDay" : {
    "y" : 1993,
    "m" : 12,
    "d" : 6
  }
}, {
  "uid" : "21675",
  "licenseId" : "14041988004",
  "country" : "BEL",
  "name" : {
    "firstName" : "Lucas",
    "lastName" : "BOSMANS",
    "fullName" : "BOSMANS, Lucas"
  },
  "gender" : "MALE",
  "hand" : "RIGHT",
  "birthDay" : {
    "y" : 1988,
    "m" : 4,
    "d" : 14
  }
}, {
  "uid" : "42039",
  "licenseId" : null,
  "country" : "BEL",
  "name" : {
    "firstName" : "Mattice",
    "lastName" : "BOSSCHEM",
    "fullName" : "BOSSCHEM, Mattice"
  },
  "gender" : "MALE",
  "hand" : "RIGHT",
  "birthDay" : {
    "y" : 1999,
    "m" : 5,
    "d" : 29
  }
}, {
  "uid" : "19779",
  "licenseId" : "13081985003",
  "country" : "BEL",
  "name" : {
    "firstName" : "Pierre Julien",
    "lastName" : "BOSSER-LAMY",
    "fullName" : "BOSSER-LAMY, Pierre Julien"
  },
  "gender" : "MALE",
  "hand" : "LEFT",
  "birthDay" : {
    "y" : 1985,
    "m" : 8,
    "d" : 13
  }
}, {
  "uid" : "38740",
  "licenseId" : "11121998001",
  "country" : "BEL",
  "name" : {
    "firstName" : "Arnaud",
    "lastName" : "BOTTECCHIA",
    "fullName" : "BOTTECCHIA, Arnaud"
  },
  "gender" : "MALE",
  "hand" : "RIGHT",
  "birthDay" : {
    "y" : 1998,
    "m" : 12,
    "d" : 11
  }
}, {
  "uid" : "33264",
  "licenseId" : "03051963000",
  "country" : "BEL",
  "name" : {
    "firstName" : "Godefroid",
    "lastName" : "BOTTECCHIA",
    "fullName" : "BOTTECCHIA, Godefroid"
  },
  "gender" : "MALE",
  "hand" : "RIGHT",
  "birthDay" : {
    "y" : 1963,
    "m" : 5,
    "d" : 3
  }
}, {
  "uid" : "39622",
  "licenseId" : "14011984004",
  "country" : "BEL",
  "name" : {
    "firstName" : "Nicolas",
    "lastName" : "BOULANGE",
    "fullName" : "BOULANGE, Nicolas"
  },
  "gender" : "MALE",
  "hand" : "RIGHT",
  "birthDay" : {
    "y" : 1984,
    "m" : 1,
    "d" : 14
  }
}, {
  "uid" : "41792",
  "licenseId" : null,
  "country" : "BEL",
  "name" : {
    "firstName" : "Brice",
    "lastName" : "BOURGUIGNON",
    "fullName" : "BOURGUIGNON, Brice"
  },
  "gender" : "MALE",
  "hand" : "RIGHT",
  "birthDay" : {
    "y" : 1998,
    "m" : 8,
    "d" : 24
  }
}, {
  "uid" : "32278",
  "licenseId" : "13041996002",
  "country" : "BEL",
  "name" : {
    "firstName" : "Robin",
    "lastName" : "BOUTTEFEUX",
    "fullName" : "BOUTTEFEUX, Robin"
  },
  "gender" : "MALE",
  "hand" : "RIGHT",
  "birthDay" : {
    "y" : 1996,
    "m" : 4,
    "d" : 13
  }
}, {
  "uid" : "21785",
  "licenseId" : "04051992000",
  "country" : "BEL",
  "name" : {
    "firstName" : "Thomas",
    "lastName" : "BOZZINI",
    "fullName" : "BOZZINI, Thomas"
  },
  "gender" : "MALE",
  "hand" : null,
  "birthDay" : {
    "y" : 1992,
    "m" : 5,
    "d" : 4
  }
}, {
  "uid" : "23600",
  "licenseId" : "27021992001",
  "country" : "BEL",
  "name" : {
    "firstName" : "Michael",
    "lastName" : "BRACKE",
    "fullName" : "BRACKE, Michael"
  },
  "gender" : "MALE",
  "hand" : "RIGHT",
  "birthDay" : {
    "y" : 1992,
    "m" : 2,
    "d" : 27
  }
}, {
  "uid" : "1723",
  "licenseId" : "20021979000",
  "country" : "BEL",
  "name" : {
    "firstName" : "Frederik",
    "lastName" : "BRAECKMAN",
    "fullName" : "BRAECKMAN, Frederik"
  },
  "gender" : "MALE",
  "hand" : null,
  "birthDay" : {
    "y" : 1979,
    "m" : 2,
    "d" : 20
  }
}, {
  "uid" : "25101",
  "licenseId" : "02011993001",
  "country" : "BEL",
  "name" : {
    "firstName" : "Alexandra",
    "lastName" : "BRASSEUR",
    "fullName" : "BRASSEUR, Alexandra"
  },
  "gender" : "FEMALE",
  "hand" : "RIGHT",
  "birthDay" : {
    "y" : 1993,
    "m" : 1,
    "d" : 2
  }
}, {
  "uid" : "17287",
  "licenseId" : "05021991000",
  "country" : "BEL",
  "name" : {
    "firstName" : "Servaas",
    "lastName" : "BREYNE",
    "fullName" : "BREYNE, Servaas"
  },
  "gender" : "MALE",
  "hand" : "LEFT",
  "birthDay" : {
    "y" : 1991,
    "m" : 2,
    "d" : 5
  }
}, {
  "uid" : "16247",
  "licenseId" : "26051979000",
  "country" : "BEL",
  "name" : {
    "firstName" : "Cyril",
    "lastName" : "BRIQUET",
    "fullName" : "BRIQUET, Cyril"
  },
  "gender" : "MALE",
  "hand" : null,
  "birthDay" : {
    "y" : 1979,
    "m" : 5,
    "d" : 26
  }
}, {
  "uid" : "1724",
  "licenseId" : "06011984001",
  "country" : "BEL",
  "name" : {
    "firstName" : "Jerome",
    "lastName" : "BROHEZ",
    "fullName" : "BROHEZ, Jerome"
  },
  "gender" : "MALE",
  "hand" : null,
  "birthDay" : {
    "y" : 1984,
    "m" : 1,
    "d" : 6
  }
}, {
  "uid" : "20792",
  "licenseId" : "22101991000",
  "country" : "BEL",
  "name" : {
    "firstName" : "Olivier",
    "lastName" : "BUREZ",
    "fullName" : "BUREZ, Olivier"
  },
  "gender" : "MALE",
  "hand" : "RIGHT",
  "birthDay" : {
    "y" : 1991,
    "m" : 10,
    "d" : 22
  }
}, {
  "uid" : "14445",
  "licenseId" : "27111987002",
  "country" : "BEL",
  "name" : {
    "firstName" : "Aurelie",
    "lastName" : "BUSINARO",
    "fullName" : "BUSINARO, Aurelie"
  },
  "gender" : "FEMALE",
  "hand" : null,
  "birthDay" : {
    "y" : 1987,
    "m" : 11,
    "d" : 27
  }
}, {
  "uid" : "25119",
  "licenseId" : "21111987008",
  "country" : "BEL",
  "name" : {
    "firstName" : "Aurelie",
    "lastName" : "BUSINARO",
    "fullName" : "BUSINARO, Aurelie"
  },
  "gender" : "FEMALE",
  "hand" : "RIGHT",
  "birthDay" : {
    "y" : 1987,
    "m" : 11,
    "d" : 21
  }
}, {
  "uid" : "10910",
  "licenseId" : "24021987000",
  "country" : "BEL",
  "name" : {
    "firstName" : "Xavier",
    "lastName" : "CAIGNET",
    "fullName" : "CAIGNET, Xavier"
  },
  "gender" : "MALE",
  "hand" : "RIGHT",
  "birthDay" : {
    "y" : 1987,
    "m" : 2,
    "d" : 24
  }
}, {
  "uid" : "32277",
  "licenseId" : "20091995003",
  "country" : "BEL",
  "name" : {
    "firstName" : "Ruben",
    "lastName" : "CALUWAERTS",
    "fullName" : "CALUWAERTS, Ruben"
  },
  "gender" : "MALE",
  "hand" : "RIGHT",
  "birthDay" : {
    "y" : 1995,
    "m" : 9,
    "d" : 20
  }
}, {
  "uid" : "21919",
  "licenseId" : "30041991002",
  "country" : "BEL",
  "name" : {
    "firstName" : "Arno",
    "lastName" : "CAMPANELLA",
    "fullName" : "CAMPANELLA, Arno"
  },
  "gender" : "MALE",
  "hand" : null,
  "birthDay" : {
    "y" : 1991,
    "m" : 4,
    "d" : 30
  }
}, {
  "uid" : "21787",
  "licenseId" : "21061970001",
  "country" : "BEL",
  "name" : {
    "firstName" : "Anthony",
    "lastName" : "CANDAELE",
    "fullName" : "CANDAELE, Anthony"
  },
  "gender" : "MALE",
  "hand" : "LEFT",
  "birthDay" : {
    "y" : 1970,
    "m" : 6,
    "d" : 21
  }
}, {
  "uid" : "32910",
  "licenseId" : "07051997001",
  "country" : "BEL",
  "name" : {
    "firstName" : "Sofia",
    "lastName" : "CAZAERCK",
    "fullName" : "CAZAERCK, Sofia"
  },
  "gender" : "FEMALE",
  "hand" : "RIGHT",
  "birthDay" : {
    "y" : 1997,
    "m" : 5,
    "d" : 7
  }
}, {
  "uid" : "15256",
  "licenseId" : "04081964000",
  "country" : "BEL",
  "name" : {
    "firstName" : "Steven",
    "lastName" : "CAZAERCK",
    "fullName" : "CAZAERCK, Steven"
  },
  "gender" : "MALE",
  "hand" : null,
  "birthDay" : {
    "y" : 1964,
    "m" : 8,
    "d" : 4
  }
}, {
  "uid" : "21783",
  "licenseId" : "18091992001",
  "country" : "BEL",
  "name" : {
    "firstName" : "Nicolas",
    "lastName" : "CHAMPAGNE",
    "fullName" : "CHAMPAGNE, Nicolas"
  },
  "gender" : "MALE",
  "hand" : "RIGHT",
  "birthDay" : {
    "y" : 1992,
    "m" : 9,
    "d" : 18
  }
}, {
  "uid" : "15980",
  "licenseId" : "29111979001",
  "country" : "BEL",
  "name" : {
    "firstName" : "Bart",
    "lastName" : "CLAESSENS",
    "fullName" : "CLAESSENS, Bart"
  },
  "gender" : "MALE",
  "hand" : "RIGHT",
  "birthDay" : {
    "y" : 1979,
    "m" : 11,
    "d" : 29
  }
}, {
  "uid" : "14418",
  "licenseId" : "03111978000",
  "country" : "BEL",
  "name" : {
    "firstName" : "Rodolphe",
    "lastName" : "CLAEYS",
    "fullName" : "CLAEYS, Rodolphe"
  },
  "gender" : "MALE",
  "hand" : "RIGHT",
  "birthDay" : {
    "y" : 1978,
    "m" : 11,
    "d" : 3
  }
}, {
  "uid" : "35826",
  "licenseId" : "04031998001",
  "country" : "BEL",
  "name" : {
    "firstName" : "Robin",
    "lastName" : "CLERCX",
    "fullName" : "CLERCX, Robin"
  },
  "gender" : "MALE",
  "hand" : "RIGHT",
  "birthDay" : {
    "y" : 1998,
    "m" : 3,
    "d" : 4
  }
}, {
  "uid" : "28369",
  "licenseId" : "20041995000",
  "country" : "BEL",
  "name" : {
    "firstName" : "Charlotte",
    "lastName" : "CLOETENS",
    "fullName" : "CLOETENS, Charlotte"
  },
  "gender" : "FEMALE",
  "hand" : "RIGHT",
  "birthDay" : {
    "y" : 1995,
    "m" : 4,
    "d" : 20
  }
}, {
  "uid" : "14481",
  "licenseId" : "02081988003",
  "country" : "BEL",
  "name" : {
    "firstName" : "Benjamin",
    "lastName" : "COCRIAMONT",
    "fullName" : "COCRIAMONT, Benjamin"
  },
  "gender" : "MALE",
  "hand" : "RIGHT",
  "birthDay" : {
    "y" : 1988,
    "m" : 8,
    "d" : 2
  }
}, {
  "uid" : "1725",
  "licenseId" : "09121973000",
  "country" : "BEL",
  "name" : {
    "firstName" : "Vincianne",
    "lastName" : "COESSENS",
    "fullName" : "COESSENS, Vincianne"
  },
  "gender" : "FEMALE",
  "hand" : null,
  "birthDay" : {
    "y" : 1973,
    "m" : 12,
    "d" : 9
  }
}, {
  "uid" : "29780",
  "licenseId" : "10071994003",
  "country" : "BEL",
  "name" : {
    "firstName" : "Jeremy",
    "lastName" : "COFINO",
    "fullName" : "COFINO, Jeremy"
  },
  "gender" : "MALE",
  "hand" : "RIGHT",
  "birthDay" : {
    "y" : 1994,
    "m" : 7,
    "d" : 10
  }
}, {
  "uid" : "17423",
  "licenseId" : "06071988002",
  "country" : "BEL",
  "name" : {
    "firstName" : "Martin",
    "lastName" : "COLARD",
    "fullName" : "COLARD, Martin"
  },
  "gender" : "MALE",
  "hand" : "RIGHT",
  "birthDay" : {
    "y" : 1988,
    "m" : 7,
    "d" : 6
  }
}, {
  "uid" : "12174",
  "licenseId" : "05041988000",
  "country" : "BEL",
  "name" : {
    "firstName" : "Bertrand",
    "lastName" : "COLIN",
    "fullName" : "COLIN, Bertrand"
  },
  "gender" : "MALE",
  "hand" : "RIGHT",
  "birthDay" : {
    "y" : 1988,
    "m" : 4,
    "d" : 5
  }
}, {
  "uid" : "1726",
  "licenseId" : "01051983001",
  "country" : "BEL",
  "name" : {
    "firstName" : "Tibault",
    "lastName" : "COLOT",
    "fullName" : "COLOT, Tibault"
  },
  "gender" : "MALE",
  "hand" : "RIGHT",
  "birthDay" : {
    "y" : 1983,
    "m" : 5,
    "d" : 1
  }
}, {
  "uid" : "25098",
  "licenseId" : "16071993002",
  "country" : "BEL",
  "name" : {
    "firstName" : "Hanne",
    "lastName" : "COOREMAN",
    "fullName" : "COOREMAN, Hanne"
  },
  "gender" : "FEMALE",
  "hand" : "RIGHT",
  "birthDay" : {
    "y" : 1993,
    "m" : 7,
    "d" : 16
  }
}, {
  "uid" : "39443",
  "licenseId" : "19102001000",
  "country" : "BEL",
  "name" : {
    "firstName" : "Jolien",
    "lastName" : "CORTEYN",
    "fullName" : "CORTEYN, Jolien"
  },
  "gender" : "FEMALE",
  "hand" : "RIGHT",
  "birthDay" : {
    "y" : 2001,
    "m" : 10,
    "d" : 19
  }
}, {
  "uid" : "36705",
  "licenseId" : "21042000000",
  "country" : "BEL",
  "name" : {
    "firstName" : "Saartje",
    "lastName" : "CORTEYN",
    "fullName" : "CORTEYN, Saartje"
  },
  "gender" : "FEMALE",
  "hand" : "RIGHT",
  "birthDay" : {
    "y" : 2000,
    "m" : 4,
    "d" : 21
  }
}, {
  "uid" : "31747",
  "licenseId" : "17111995002",
  "country" : "BEL",
  "name" : {
    "firstName" : "Nicolas",
    "lastName" : "COULAIE",
    "fullName" : "COULAIE, Nicolas"
  },
  "gender" : "MALE",
  "hand" : "RIGHT",
  "birthDay" : {
    "y" : 1995,
    "m" : 11,
    "d" : 17
  }
}, {
  "uid" : "35839",
  "licenseId" : "11021998001",
  "country" : "BEL",
  "name" : {
    "firstName" : "Tom",
    "lastName" : "CRNJAK",
    "fullName" : "CRNJAK, Tom"
  },
  "gender" : "MALE",
  "hand" : "RIGHT",
  "birthDay" : {
    "y" : 1998,
    "m" : 2,
    "d" : 11
  }
}, {
  "uid" : "1737",
  "licenseId" : "09111984001",
  "country" : "BEL",
  "name" : {
    "firstName" : "Matthias",
    "lastName" : "D'HAENE",
    "fullName" : "D'HAENE, Matthias"
  },
  "gender" : "MALE",
  "hand" : "RIGHT",
  "birthDay" : {
    "y" : 1984,
    "m" : 11,
    "d" : 9
  }
}, {
  "uid" : "13133",
  "licenseId" : "07111988002",
  "country" : "BEL",
  "name" : {
    "firstName" : "Olivier",
    "lastName" : "DAWIRS",
    "fullName" : "DAWIRS, Olivier"
  },
  "gender" : "MALE",
  "hand" : "RIGHT",
  "birthDay" : {
    "y" : 1988,
    "m" : 11,
    "d" : 7
  }
}, {
  "uid" : "18001",
  "licenseId" : "03061990001",
  "country" : "BEL",
  "name" : {
    "firstName" : "Thales",
    "lastName" : "DE BRANT",
    "fullName" : "DE BRANT, Thales"
  },
  "gender" : "MALE",
  "hand" : "LEFT",
  "birthDay" : {
    "y" : 1990,
    "m" : 6,
    "d" : 3
  }
}, {
  "uid" : "33542",
  "licenseId" : "22051996004",
  "country" : "BEL",
  "name" : {
    "firstName" : "Henri",
    "lastName" : "DE CLERCQ",
    "fullName" : "DE CLERCQ, Henri"
  },
  "gender" : "MALE",
  "hand" : "RIGHT",
  "birthDay" : {
    "y" : 1996,
    "m" : 5,
    "d" : 22
  }
}, {
  "uid" : "33543",
  "licenseId" : "24041995004",
  "country" : "BEL",
  "name" : {
    "firstName" : "David",
    "lastName" : "DE DONDER",
    "fullName" : "DE DONDER, David"
  },
  "gender" : "MALE",
  "hand" : "RIGHT",
  "birthDay" : {
    "y" : 1995,
    "m" : 4,
    "d" : 24
  }
}, {
  "uid" : "19725",
  "licenseId" : "30061969002",
  "country" : "BEL",
  "name" : {
    "firstName" : "Thierry",
    "lastName" : "DE FORET",
    "fullName" : "DE FORET, Thierry"
  },
  "gender" : "MALE",
  "hand" : "RIGHT",
  "birthDay" : {
    "y" : 1969,
    "m" : 6,
    "d" : 30
  }
}, {
  "uid" : "35143",
  "licenseId" : "10011998001",
  "country" : "BEL",
  "name" : {
    "firstName" : "Stef",
    "lastName" : "DE GREEF",
    "fullName" : "DE GREEF, Stef"
  },
  "gender" : "MALE",
  "hand" : "LEFT",
  "birthDay" : {
    "y" : 1998,
    "m" : 1,
    "d" : 10
  }
}, {
  "uid" : "22917",
  "licenseId" : "30111985003",
  "country" : "BEL",
  "name" : {
    "firstName" : "Elise",
    "lastName" : "DE LOOF",
    "fullName" : "DE LOOF, Elise"
  },
  "gender" : "FEMALE",
  "hand" : "RIGHT",
  "birthDay" : {
    "y" : 1985,
    "m" : 11,
    "d" : 30
  }
}, {
  "uid" : "17193",
  "licenseId" : "30061991000",
  "country" : "BEL",
  "name" : {
    "firstName" : "Francois",
    "lastName" : "DE MEESTER",
    "fullName" : "DE MEESTER, Francois"
  },
  "gender" : "MALE",
  "hand" : "RIGHT",
  "birthDay" : {
    "y" : 1991,
    "m" : 6,
    "d" : 30
  }
}, {
  "uid" : "10907",
  "licenseId" : "23071988000",
  "country" : "BEL",
  "name" : {
    "firstName" : "Germain",
    "lastName" : "DE MEESTER",
    "fullName" : "DE MEESTER, Germain"
  },
  "gender" : "MALE",
  "hand" : "RIGHT",
  "birthDay" : {
    "y" : 1988,
    "m" : 7,
    "d" : 23
  }
}, {
  "uid" : "18002",
  "licenseId" : "03081990001",
  "country" : "BEL",
  "name" : {
    "firstName" : "Bert",
    "lastName" : "DE METS",
    "fullName" : "DE METS, Bert"
  },
  "gender" : "MALE",
  "hand" : "LEFT",
  "birthDay" : {
    "y" : 1990,
    "m" : 8,
    "d" : 3
  }
}, {
  "uid" : "14874",
  "licenseId" : "09031955000",
  "country" : "BEL",
  "name" : {
    "firstName" : "Ellie",
    "lastName" : "DE MOL",
    "fullName" : "DE MOL, Ellie"
  },
  "gender" : "FEMALE",
  "hand" : "RIGHT",
  "birthDay" : {
    "y" : 1955,
    "m" : 3,
    "d" : 9
  }
}, {
  "uid" : "19687",
  "licenseId" : "29041990001",
  "country" : "BEL",
  "name" : {
    "firstName" : "Lander",
    "lastName" : "DE PAUW",
    "fullName" : "DE PAUW, Lander"
  },
  "gender" : "MALE",
  "hand" : "RIGHT",
  "birthDay" : {
    "y" : 1990,
    "m" : 4,
    "d" : 29
  }
}, {
  "uid" : "14543",
  "licenseId" : "10081988001",
  "country" : "BEL",
  "name" : {
    "firstName" : "Amber",
    "lastName" : "DE PESTEL",
    "fullName" : "DE PESTEL, Amber"
  },
  "gender" : "FEMALE",
  "hand" : "RIGHT",
  "birthDay" : {
    "y" : 1988,
    "m" : 8,
    "d" : 10
  }
}, {
  "uid" : "18977",
  "licenseId" : "15011974001",
  "country" : "BEL",
  "name" : {
    "firstName" : "Mirella",
    "lastName" : "DE RECHTER",
    "fullName" : "DE RECHTER, Mirella"
  },
  "gender" : "FEMALE",
  "hand" : "RIGHT",
  "birthDay" : {
    "y" : 1974,
    "m" : 1,
    "d" : 15
  }
}, {
  "uid" : "35917",
  "licenseId" : "27032000000",
  "country" : "BEL",
  "name" : {
    "firstName" : "Arne",
    "lastName" : "DE RIDDER",
    "fullName" : "DE RIDDER, Arne"
  },
  "gender" : "MALE",
  "hand" : "RIGHT",
  "birthDay" : {
    "y" : 2000,
    "m" : 3,
    "d" : 27
  }
}, {
  "uid" : "9613",
  "licenseId" : "12091959001",
  "country" : "BEL",
  "name" : {
    "firstName" : "Daniel",
    "lastName" : "DE ROECK",
    "fullName" : "DE ROECK, Daniel"
  },
  "gender" : "MALE",
  "hand" : "RIGHT",
  "birthDay" : {
    "y" : 1959,
    "m" : 9,
    "d" : 12
  }
}, {
  "uid" : "9665",
  "licenseId" : "08081986002",
  "country" : "BEL",
  "name" : {
    "firstName" : "Laurent",
    "lastName" : "DE TROG",
    "fullName" : "DE TROG, Laurent"
  },
  "gender" : "MALE",
  "hand" : "RIGHT",
  "birthDay" : {
    "y" : 1986,
    "m" : 8,
    "d" : 8
  }
}, {
  "uid" : "23263",
  "licenseId" : "09041991002",
  "country" : "BEL",
  "name" : {
    "firstName" : "Antoine",
    "lastName" : "DE VILLEGAS",
    "fullName" : "DE VILLEGAS, Antoine"
  },
  "gender" : "MALE",
  "hand" : "LEFT",
  "birthDay" : {
    "y" : 1991,
    "m" : 4,
    "d" : 9
  }
}, {
  "uid" : "26203",
  "licenseId" : "13071995001",
  "country" : "BEL",
  "name" : {
    "firstName" : "Jules-Emile",
    "lastName" : "DE VISSCHER",
    "fullName" : "DE VISSCHER, Jules-Emile"
  },
  "gender" : "MALE",
  "hand" : "RIGHT",
  "birthDay" : {
    "y" : 1995,
    "m" : 7,
    "d" : 13
  }
}, {
  "uid" : "28145",
  "licenseId" : "29071995002",
  "country" : "BEL",
  "name" : {
    "firstName" : "Pieter",
    "lastName" : "DE VOS",
    "fullName" : "DE VOS, Pieter"
  },
  "gender" : "MALE",
  "hand" : "RIGHT",
  "birthDay" : {
    "y" : 1995,
    "m" : 7,
    "d" : 29
  }
}, {
  "uid" : "10068",
  "licenseId" : "15121985002",
  "country" : "BEL",
  "name" : {
    "firstName" : "Thomas",
    "lastName" : "DE WILDE",
    "fullName" : "DE WILDE, Thomas"
  },
  "gender" : "MALE",
  "hand" : "RIGHT",
  "birthDay" : {
    "y" : 1985,
    "m" : 12,
    "d" : 15
  }
}, {
  "uid" : "1729",
  "licenseId" : "30041985000",
  "country" : "BEL",
  "name" : {
    "firstName" : "Tiffany",
    "lastName" : "DE-CLERCQ",
    "fullName" : "DE-CLERCQ, Tiffany"
  },
  "gender" : "FEMALE",
  "hand" : "RIGHT",
  "birthDay" : {
    "y" : 1985,
    "m" : 4,
    "d" : 30
  }
}, {
  "uid" : "26205",
  "licenseId" : "01081990003",
  "country" : "BEL",
  "name" : {
    "firstName" : "Quentin",
    "lastName" : "DEBATY",
    "fullName" : "DEBATY, Quentin"
  },
  "gender" : "MALE",
  "hand" : "RIGHT",
  "birthDay" : {
    "y" : 1990,
    "m" : 8,
    "d" : 1
  }
}, {
  "uid" : "23888",
  "licenseId" : "31101991003",
  "country" : "BEL",
  "name" : {
    "firstName" : "Benjamin",
    "lastName" : "DECHAMPS",
    "fullName" : "DECHAMPS, Benjamin"
  },
  "gender" : "MALE",
  "hand" : "RIGHT",
  "birthDay" : {
    "y" : 1991,
    "m" : 10,
    "d" : 31
  }
}, {
  "uid" : "14361",
  "licenseId" : "06101989001",
  "country" : "BEL",
  "name" : {
    "firstName" : "Quentin",
    "lastName" : "DECHAMPS",
    "fullName" : "DECHAMPS, Quentin"
  },
  "gender" : "MALE",
  "hand" : "RIGHT",
  "birthDay" : {
    "y" : 1989,
    "m" : 10,
    "d" : 6
  }
}, {
  "uid" : "10915",
  "licenseId" : "30061969000",
  "country" : "BEL",
  "name" : {
    "firstName" : "Thierry",
    "lastName" : "DEFORET",
    "fullName" : "DEFORET, Thierry"
  },
  "gender" : "MALE",
  "hand" : "RIGHT",
  "birthDay" : {
    "y" : 1969,
    "m" : 6,
    "d" : 30
  }
}, {
  "uid" : "28116",
  "licenseId" : "12101994002",
  "country" : "BEL",
  "name" : {
    "firstName" : "Maryann",
    "lastName" : "DEFRANCE",
    "fullName" : "DEFRANCE, Maryann"
  },
  "gender" : "FEMALE",
  "hand" : "RIGHT",
  "birthDay" : {
    "y" : 1994,
    "m" : 10,
    "d" : 12
  }
}, {
  "uid" : "19686",
  "licenseId" : "23031989005",
  "country" : "BEL",
  "name" : {
    "firstName" : "Jeroen",
    "lastName" : "DEHAESE",
    "fullName" : "DEHAESE, Jeroen"
  },
  "gender" : "MALE",
  "hand" : "RIGHT",
  "birthDay" : {
    "y" : 1989,
    "m" : 3,
    "d" : 23
  }
}, {
  "uid" : "1732",
  "licenseId" : "26011986000",
  "country" : "BEL",
  "name" : {
    "firstName" : "Jeffrey",
    "lastName" : "DELATTRE",
    "fullName" : "DELATTRE, Jeffrey"
  },
  "gender" : "MALE",
  "hand" : "RIGHT",
  "birthDay" : {
    "y" : 1986,
    "m" : 1,
    "d" : 26
  }
}, {
  "uid" : "17092",
  "licenseId" : "26011988001",
  "country" : "BEL",
  "name" : {
    "firstName" : "Jonathan",
    "lastName" : "DELCOURT",
    "fullName" : "DELCOURT, Jonathan"
  },
  "gender" : "MALE",
  "hand" : "RIGHT",
  "birthDay" : {
    "y" : 1988,
    "m" : 1,
    "d" : 26
  }
}, {
  "uid" : "23748",
  "licenseId" : "24061992003",
  "country" : "BEL",
  "name" : {
    "firstName" : "Rik",
    "lastName" : "DEMAEREL",
    "fullName" : "DEMAEREL, Rik"
  },
  "gender" : "MALE",
  "hand" : "RIGHT",
  "birthDay" : {
    "y" : 1992,
    "m" : 6,
    "d" : 24
  }
}, {
  "uid" : "28144",
  "licenseId" : "04121996000",
  "country" : "BEL",
  "name" : {
    "firstName" : "Ian",
    "lastName" : "DENTANT",
    "fullName" : "DENTANT, Ian"
  },
  "gender" : "MALE",
  "hand" : "LEFT",
  "birthDay" : {
    "y" : 1996,
    "m" : 12,
    "d" : 4
  }
}, {
  "uid" : "42771",
  "licenseId" : null,
  "country" : "BEL",
  "name" : {
    "firstName" : "Helene",
    "lastName" : "DERDE",
    "fullName" : "DERDE, Helene"
  },
  "gender" : null,
  "hand" : null,
  "birthDay" : {
    "y" : 1999,
    "m" : 6,
    "d" : 27
  }
}, {
  "uid" : "23944",
  "licenseId" : "14121992002",
  "country" : "BEL",
  "name" : {
    "firstName" : "Marie",
    "lastName" : "DESCHUYTTER",
    "fullName" : "DESCHUYTTER, Marie"
  },
  "gender" : "FEMALE",
  "hand" : "LEFT",
  "birthDay" : {
    "y" : 1992,
    "m" : 12,
    "d" : 14
  }
}, {
  "uid" : "29895",
  "licenseId" : "14081994003",
  "country" : "BEL",
  "name" : {
    "firstName" : "Yannick",
    "lastName" : "DESEMBERG",
    "fullName" : "DESEMBERG, Yannick"
  },
  "gender" : "MALE",
  "hand" : "RIGHT",
  "birthDay" : {
    "y" : 1994,
    "m" : 8,
    "d" : 14
  }
}, {
  "uid" : "34257",
  "licenseId" : "23071996004",
  "country" : "BEL",
  "name" : {
    "firstName" : "Florian",
    "lastName" : "DEWANDELEER",
    "fullName" : "DEWANDELEER, Florian"
  },
  "gender" : "MALE",
  "hand" : "RIGHT",
  "birthDay" : {
    "y" : 1996,
    "m" : 7,
    "d" : 23
  }
}, {
  "uid" : "33816",
  "licenseId" : "29111996000",
  "country" : "BEL",
  "name" : {
    "firstName" : "Carlotta",
    "lastName" : "DHAEYER",
    "fullName" : "DHAEYER, Carlotta"
  },
  "gender" : "FEMALE",
  "hand" : "RIGHT",
  "birthDay" : {
    "y" : 1996,
    "m" : 11,
    "d" : 29
  }
}, {
  "uid" : "12175",
  "licenseId" : "01031989001",
  "country" : "BEL",
  "name" : {
    "firstName" : "Thomas",
    "lastName" : "DOMBARD",
    "fullName" : "DOMBARD, Thomas"
  },
  "gender" : "MALE",
  "hand" : "RIGHT",
  "birthDay" : {
    "y" : 1989,
    "m" : 3,
    "d" : 1
  }
}, {
  "uid" : "39194",
  "licenseId" : "29101998001",
  "country" : "BEL",
  "name" : {
    "firstName" : "Laura",
    "lastName" : "DON",
    "fullName" : "DON, Laura"
  },
  "gender" : "FEMALE",
  "hand" : "RIGHT",
  "birthDay" : {
    "y" : 1998,
    "m" : 10,
    "d" : 29
  }
}, {
  "uid" : "28184",
  "licenseId" : "22091975000",
  "country" : "BEL",
  "name" : {
    "firstName" : "Alexis",
    "lastName" : "DONNE",
    "fullName" : "DONNE, Alexis"
  },
  "gender" : "MALE",
  "hand" : "RIGHT",
  "birthDay" : {
    "y" : 1975,
    "m" : 9,
    "d" : 22
  }
}, {
  "uid" : "10908",
  "licenseId" : "02021988000",
  "country" : "BEL",
  "name" : {
    "firstName" : "Bertrand",
    "lastName" : "DUMONT",
    "fullName" : "DUMONT, Bertrand"
  },
  "gender" : "MALE",
  "hand" : "LEFT",
  "birthDay" : {
    "y" : 1988,
    "m" : 2,
    "d" : 2
  }
}, {
  "uid" : "17499",
  "licenseId" : "27101988000",
  "country" : "BEL",
  "name" : {
    "firstName" : "Gautier",
    "lastName" : "DUMONT",
    "fullName" : "DUMONT, Gautier"
  },
  "gender" : "MALE",
  "hand" : "RIGHT",
  "birthDay" : {
    "y" : 1988,
    "m" : 10,
    "d" : 27
  }
}, {
  "uid" : "18409",
  "licenseId" : "08021990002",
  "country" : "BEL",
  "name" : {
    "firstName" : "Quentin",
    "lastName" : "DUPONT",
    "fullName" : "DUPONT, Quentin"
  },
  "gender" : "MALE",
  "hand" : "RIGHT",
  "birthDay" : {
    "y" : 1990,
    "m" : 2,
    "d" : 8
  }
}, {
  "uid" : "7684",
  "licenseId" : "24061970000",
  "country" : "BEL",
  "name" : {
    "firstName" : "Jean-Markus",
    "lastName" : "EGGERMONT",
    "fullName" : "EGGERMONT, Jean-Markus"
  },
  "gender" : "MALE",
  "hand" : "RIGHT",
  "birthDay" : {
    "y" : 1970,
    "m" : 6,
    "d" : 24
  }
}, {
  "uid" : "17283",
  "licenseId" : "03011986008",
  "country" : "BEL",
  "name" : {
    "firstName" : "Jonathan",
    "lastName" : "EVRARD",
    "fullName" : "EVRARD, Jonathan"
  },
  "gender" : "MALE",
  "hand" : "RIGHT",
  "birthDay" : {
    "y" : 1986,
    "m" : 1,
    "d" : 3
  }
}, {
  "uid" : "14484",
  "licenseId" : "25101983002",
  "country" : "BEL",
  "name" : {
    "firstName" : "Laurent",
    "lastName" : "FANIEL",
    "fullName" : "FANIEL, Laurent"
  },
  "gender" : "MALE",
  "hand" : "RIGHT",
  "birthDay" : {
    "y" : 1983,
    "m" : 10,
    "d" : 25
  }
}, {
  "uid" : "40855",
  "licenseId" : "15101999003",
  "country" : "BEL",
  "name" : {
    "firstName" : "Basile-Vladimir",
    "lastName" : "FAUCONNIER",
    "fullName" : "FAUCONNIER, Basile-Vladimir"
  },
  "gender" : "MALE",
  "hand" : "RIGHT",
  "birthDay" : {
    "y" : 1999,
    "m" : 10,
    "d" : 15
  }
}, {
  "uid" : "1739",
  "licenseId" : "09051987001",
  "country" : "BEL",
  "name" : {
    "firstName" : "Ernst",
    "lastName" : "FELIX",
    "fullName" : "FELIX, Ernst"
  },
  "gender" : "MALE",
  "hand" : "RIGHT",
  "birthDay" : {
    "y" : 1987,
    "m" : 5,
    "d" : 9
  }
}, {
  "uid" : "15010",
  "licenseId" : "16081988002",
  "country" : "BEL",
  "name" : {
    "firstName" : "Thibault",
    "lastName" : "FERAGE",
    "fullName" : "FERAGE, Thibault"
  },
  "gender" : "MALE",
  "hand" : "RIGHT",
  "birthDay" : {
    "y" : 1988,
    "m" : 8,
    "d" : 16
  }
}, {
  "uid" : "21916",
  "licenseId" : "05031991002",
  "country" : "BEL",
  "name" : {
    "firstName" : "Francois Xavier",
    "lastName" : "FEROT",
    "fullName" : "FEROT, Francois Xavier"
  },
  "gender" : "MALE",
  "hand" : "RIGHT",
  "birthDay" : {
    "y" : 1991,
    "m" : 3,
    "d" : 5
  }
}, {
  "uid" : "17192",
  "licenseId" : "13011980001",
  "country" : "BEL",
  "name" : {
    "firstName" : "Guy",
    "lastName" : "FOCANT",
    "fullName" : "FOCANT, Guy"
  },
  "gender" : "MALE",
  "hand" : "RIGHT",
  "birthDay" : {
    "y" : 1980,
    "m" : 1,
    "d" : 13
  }
}, {
  "uid" : "40854",
  "licenseId" : "05051999002",
  "country" : "BEL",
  "name" : {
    "firstName" : "Hugo",
    "lastName" : "FRERES",
    "fullName" : "FRERES, Hugo"
  },
  "gender" : "MALE",
  "hand" : "RIGHT",
  "birthDay" : {
    "y" : 1999,
    "m" : 5,
    "d" : 5
  }
}, {
  "uid" : "34009",
  "licenseId" : "30031996004",
  "country" : "BEL",
  "name" : {
    "firstName" : "Georges",
    "lastName" : "FROMONT",
    "fullName" : "FROMONT, Georges"
  },
  "gender" : "MALE",
  "hand" : "RIGHT",
  "birthDay" : {
    "y" : 1996,
    "m" : 3,
    "d" : 30
  }
}, {
  "uid" : "29808",
  "licenseId" : "29081991006",
  "country" : "BEL",
  "name" : {
    "firstName" : "Kevin",
    "lastName" : "FUKS",
    "fullName" : "FUKS, Kevin"
  },
  "gender" : "MALE",
  "hand" : "RIGHT",
  "birthDay" : {
    "y" : 1991,
    "m" : 8,
    "d" : 29
  }
}, {
  "uid" : "28255",
  "licenseId" : "27051993003",
  "country" : "BEL",
  "name" : {
    "firstName" : "Guillaume",
    "lastName" : "GEORGES",
    "fullName" : "GEORGES, Guillaume"
  },
  "gender" : "MALE",
  "hand" : "RIGHT",
  "birthDay" : {
    "y" : 1993,
    "m" : 5,
    "d" : 27
  }
}, {
  "uid" : "9592",
  "licenseId" : "05081986005",
  "country" : "BEL",
  "name" : {
    "firstName" : "Yannick",
    "lastName" : "GERMEAU",
    "fullName" : "GERMEAU, Yannick"
  },
  "gender" : "MALE",
  "hand" : "RIGHT",
  "birthDay" : {
    "y" : 1986,
    "m" : 8,
    "d" : 5
  }
}, {
  "uid" : "30152",
  "licenseId" : "24101996001",
  "country" : "BEL",
  "name" : {
    "firstName" : "Alexandra",
    "lastName" : "GEVAERT",
    "fullName" : "GEVAERT, Alexandra"
  },
  "gender" : "FEMALE",
  "hand" : "RIGHT",
  "birthDay" : {
    "y" : 1996,
    "m" : 10,
    "d" : 24
  }
}, {
  "uid" : "28119",
  "licenseId" : "04041995000",
  "country" : "BEL",
  "name" : {
    "firstName" : "Vincent",
    "lastName" : "GEVAERT",
    "fullName" : "GEVAERT, Vincent"
  },
  "gender" : "MALE",
  "hand" : "RIGHT",
  "birthDay" : {
    "y" : 1995,
    "m" : 4,
    "d" : 4
  }
}, {
  "uid" : "17288",
  "licenseId" : "15061988006",
  "country" : "BEL",
  "name" : {
    "firstName" : "Laurent",
    "lastName" : "GHIJS",
    "fullName" : "GHIJS, Laurent"
  },
  "gender" : "MALE",
  "hand" : "RIGHT",
  "birthDay" : {
    "y" : 1988,
    "m" : 6,
    "d" : 15
  }
}, {
  "uid" : "35827",
  "licenseId" : "06121997000",
  "country" : "BEL",
  "name" : {
    "firstName" : "Henri",
    "lastName" : "GILLARD",
    "fullName" : "GILLARD, Henri"
  },
  "gender" : "MALE",
  "hand" : "RIGHT",
  "birthDay" : {
    "y" : 1997,
    "m" : 12,
    "d" : 6
  }
}, {
  "uid" : "1742",
  "licenseId" : "16121985000",
  "country" : "BEL",
  "name" : {
    "firstName" : "Berangere",
    "lastName" : "GOHY",
    "fullName" : "GOHY, Berangere"
  },
  "gender" : "FEMALE",
  "hand" : "RIGHT",
  "birthDay" : {
    "y" : 1985,
    "m" : 12,
    "d" : 16
  }
}, {
  "uid" : "1743",
  "licenseId" : "16021975000",
  "country" : "BEL",
  "name" : {
    "firstName" : "Cedric",
    "lastName" : "GOHY",
    "fullName" : "GOHY, Cedric"
  },
  "gender" : "MALE",
  "hand" : "RIGHT",
  "birthDay" : {
    "y" : 1975,
    "m" : 2,
    "d" : 16
  }
}, {
  "uid" : "41790",
  "licenseId" : null,
  "country" : "BEL",
  "name" : {
    "firstName" : "Andreo",
    "lastName" : "GOORIS",
    "fullName" : "GOORIS, Andreo"
  },
  "gender" : null,
  "hand" : null,
  "birthDay" : {
    "y" : 1999,
    "m" : 10,
    "d" : 18
  }
}, {
  "uid" : "12187",
  "licenseId" : "12071989000",
  "country" : "BEL",
  "name" : {
    "firstName" : "Delphine",
    "lastName" : "GROSLAMBERT",
    "fullName" : "GROSLAMBERT, Delphine"
  },
  "gender" : "FEMALE",
  "hand" : "RIGHT",
  "birthDay" : {
    "y" : 1989,
    "m" : 7,
    "d" : 12
  }
}, {
  "uid" : "1747",
  "licenseId" : "01051987001",
  "country" : "BEL",
  "name" : {
    "firstName" : "Julie",
    "lastName" : "GROSLAMBERT",
    "fullName" : "GROSLAMBERT, Julie"
  },
  "gender" : "FEMALE",
  "hand" : "RIGHT",
  "birthDay" : {
    "y" : 1987,
    "m" : 5,
    "d" : 1
  }
}, {
  "uid" : "38747",
  "licenseId" : "05091997006",
  "country" : "BEL",
  "name" : {
    "firstName" : "Aymeric",
    "lastName" : "GUIOT",
    "fullName" : "GUIOT, Aymeric"
  },
  "gender" : "MALE",
  "hand" : "RIGHT",
  "birthDay" : {
    "y" : 1997,
    "m" : 5,
    "d" : 9
  }
}, {
  "uid" : "41789",
  "licenseId" : null,
  "country" : "BEL",
  "name" : {
    "firstName" : "Maxime",
    "lastName" : "HABRAN",
    "fullName" : "HABRAN, Maxime"
  },
  "gender" : null,
  "hand" : null,
  "birthDay" : {
    "y" : 2000,
    "m" : 12,
    "d" : 4
  }
}, {
  "uid" : "29891",
  "licenseId" : "08021995003",
  "country" : "BEL",
  "name" : {
    "firstName" : "Gautier",
    "lastName" : "HAMOLINE",
    "fullName" : "HAMOLINE, Gautier"
  },
  "gender" : "MALE",
  "hand" : "RIGHT",
  "birthDay" : {
    "y" : 1995,
    "m" : 2,
    "d" : 8
  }
}, {
  "uid" : "37942",
  "licenseId" : "03091998004",
  "country" : "BEL",
  "name" : {
    "firstName" : "Charles",
    "lastName" : "HANKENNE",
    "fullName" : "HANKENNE, Charles"
  },
  "gender" : "MALE",
  "hand" : "RIGHT",
  "birthDay" : {
    "y" : 1998,
    "m" : 9,
    "d" : 3
  }
}, {
  "uid" : "34435",
  "licenseId" : "06051996001",
  "country" : "BEL",
  "name" : {
    "firstName" : "Guillaume",
    "lastName" : "HANKENNE",
    "fullName" : "HANKENNE, Guillaume"
  },
  "gender" : "MALE",
  "hand" : "RIGHT",
  "birthDay" : {
    "y" : 1996,
    "m" : 5,
    "d" : 6
  }
}, {
  "uid" : "37000",
  "licenseId" : "12091981003",
  "country" : "BEL",
  "name" : {
    "firstName" : "Jeroen",
    "lastName" : "HANSELAER",
    "fullName" : "HANSELAER, Jeroen"
  },
  "gender" : "MALE",
  "hand" : "RIGHT",
  "birthDay" : {
    "y" : 1981,
    "m" : 9,
    "d" : 12
  }
}, {
  "uid" : "36346",
  "licenseId" : "05091996007",
  "country" : "BEL",
  "name" : {
    "firstName" : "Maurane",
    "lastName" : "HANSENNE",
    "fullName" : "HANSENNE, Maurane"
  },
  "gender" : "FEMALE",
  "hand" : "LEFT",
  "birthDay" : {
    "y" : 1996,
    "m" : 9,
    "d" : 5
  }
}, {
  "uid" : "10038",
  "licenseId" : "14021973000",
  "country" : "BEL",
  "name" : {
    "firstName" : "David Olivier",
    "lastName" : "HAULOTTE",
    "fullName" : "HAULOTTE, David Olivier"
  },
  "gender" : "MALE",
  "hand" : null,
  "birthDay" : {
    "y" : 1973,
    "m" : 2,
    "d" : 14
  }
}, {
  "uid" : "15011",
  "licenseId" : "22011987002",
  "country" : "BEL",
  "name" : {
    "firstName" : "Charles-Thibault",
    "lastName" : "HELON",
    "fullName" : "HELON, Charles-Thibault"
  },
  "gender" : "MALE",
  "hand" : "LEFT",
  "birthDay" : {
    "y" : 1987,
    "m" : 1,
    "d" : 22
  }
}, {
  "uid" : "37859",
  "licenseId" : "09011998002",
  "country" : "BEL",
  "name" : {
    "firstName" : "Robbe",
    "lastName" : "HEMELAERS",
    "fullName" : "HEMELAERS, Robbe"
  },
  "gender" : "MALE",
  "hand" : "RIGHT",
  "birthDay" : {
    "y" : 1998,
    "m" : 1,
    "d" : 9
  }
}, {
  "uid" : "30153",
  "licenseId" : "08071996002",
  "country" : "BEL",
  "name" : {
    "firstName" : "Justine",
    "lastName" : "HENDRICKX",
    "fullName" : "HENDRICKX, Justine"
  },
  "gender" : "FEMALE",
  "hand" : "LEFT",
  "birthDay" : {
    "y" : 1996,
    "m" : 7,
    "d" : 8
  }
}, {
  "uid" : "25856",
  "licenseId" : "08021995000",
  "country" : "BEL",
  "name" : {
    "firstName" : "William",
    "lastName" : "HERMAL",
    "fullName" : "HERMAL, William"
  },
  "gender" : "MALE",
  "hand" : "RIGHT",
  "birthDay" : {
    "y" : 1995,
    "m" : 2,
    "d" : 8
  }
}, {
  "uid" : "1750",
  "licenseId" : "26011984003",
  "country" : "BEL",
  "name" : {
    "firstName" : "Francois",
    "lastName" : "HERMAN",
    "fullName" : "HERMAN, Francois"
  },
  "gender" : "MALE",
  "hand" : null,
  "birthDay" : {
    "y" : 1984,
    "m" : 1,
    "d" : 26
  }
}, {
  "uid" : "39654",
  "licenseId" : "26051999002",
  "country" : "BEL",
  "name" : {
    "firstName" : "Emma",
    "lastName" : "HERMESSE",
    "fullName" : "HERMESSE, Emma"
  },
  "gender" : "FEMALE",
  "hand" : "RIGHT",
  "birthDay" : {
    "y" : 1999,
    "m" : 5,
    "d" : 26
  }
}, {
  "uid" : "31748",
  "licenseId" : "11081996000",
  "country" : "BEL",
  "name" : {
    "firstName" : "Antoine",
    "lastName" : "HONET",
    "fullName" : "HONET, Antoine"
  },
  "gender" : "MALE",
  "hand" : "RIGHT",
  "birthDay" : {
    "y" : 1996,
    "m" : 8,
    "d" : 11
  }
}, {
  "uid" : "10039",
  "licenseId" : "26061975001",
  "country" : "BEL",
  "name" : {
    "firstName" : "Damien",
    "lastName" : "HOUBEN",
    "fullName" : "HOUBEN, Damien"
  },
  "gender" : "MALE",
  "hand" : null,
  "birthDay" : {
    "y" : 1975,
    "m" : 6,
    "d" : 26
  }
}, {
  "uid" : "29923",
  "licenseId" : "12021993001",
  "country" : "BEL",
  "name" : {
    "firstName" : "Geoffroy",
    "lastName" : "HUSSON",
    "fullName" : "HUSSON, Geoffroy"
  },
  "gender" : "MALE",
  "hand" : "RIGHT",
  "birthDay" : {
    "y" : 1993,
    "m" : 2,
    "d" : 12
  }
}, {
  "uid" : "29894",
  "licenseId" : "31011995001",
  "country" : "BEL",
  "name" : {
    "firstName" : "Gijs",
    "lastName" : "HUYBRECHT",
    "fullName" : "HUYBRECHT, Gijs"
  },
  "gender" : "MALE",
  "hand" : "RIGHT",
  "birthDay" : {
    "y" : 1995,
    "m" : 1,
    "d" : 31
  }
}, {
  "uid" : "1752",
  "licenseId" : "03101983001",
  "country" : "BEL",
  "name" : {
    "firstName" : "Kevin",
    "lastName" : "INGELBRECHT",
    "fullName" : "INGELBRECHT, Kevin"
  },
  "gender" : "MALE",
  "hand" : null,
  "birthDay" : {
    "y" : 1983,
    "m" : 10,
    "d" : 3
  }
}, {
  "uid" : "17124",
  "licenseId" : "28041982003",
  "country" : "BEL",
  "name" : {
    "firstName" : "Francois Xavier",
    "lastName" : "JACOBS",
    "fullName" : "JACOBS, Francois Xavier"
  },
  "gender" : "MALE",
  "hand" : null,
  "birthDay" : {
    "y" : 1982,
    "m" : 4,
    "d" : 28
  }
}, {
  "uid" : "29809",
  "licenseId" : "19011995001",
  "country" : "BEL",
  "name" : {
    "firstName" : "Philippe",
    "lastName" : "JACQUES",
    "fullName" : "JACQUES, Philippe"
  },
  "gender" : "MALE",
  "hand" : "RIGHT",
  "birthDay" : {
    "y" : 1995,
    "m" : 1,
    "d" : 19
  }
}, {
  "uid" : "25867",
  "licenseId" : "20021992006",
  "country" : "BEL",
  "name" : {
    "firstName" : "Benoit",
    "lastName" : "KENSIER",
    "fullName" : "KENSIER, Benoit"
  },
  "gender" : "MALE",
  "hand" : "RIGHT",
  "birthDay" : {
    "y" : 1992,
    "m" : 2,
    "d" : 20
  }
}, {
  "uid" : "1753",
  "licenseId" : "09071971000",
  "country" : "BEL",
  "name" : {
    "firstName" : "Berangere",
    "lastName" : "LAHAUT",
    "fullName" : "LAHAUT, Berangere"
  },
  "gender" : "FEMALE",
  "hand" : null,
  "birthDay" : {
    "y" : 1971,
    "m" : 7,
    "d" : 9
  }
}, {
  "uid" : "15978",
  "licenseId" : "05091988002",
  "country" : "BEL",
  "name" : {
    "firstName" : "Celine",
    "lastName" : "LAKAIE",
    "fullName" : "LAKAIE, Celine"
  },
  "gender" : "FEMALE",
  "hand" : null,
  "birthDay" : {
    "y" : 1988,
    "m" : 9,
    "d" : 5
  }
}, {
  "uid" : "33821",
  "licenseId" : "10011997000",
  "country" : "BEL",
  "name" : {
    "firstName" : "Jo",
    "lastName" : "LAMBRECHTS",
    "fullName" : "LAMBRECHTS, Jo"
  },
  "gender" : "MALE",
  "hand" : "RIGHT",
  "birthDay" : {
    "y" : 1997,
    "m" : 1,
    "d" : 10
  }
}, {
  "uid" : "25100",
  "licenseId" : "13031993002",
  "country" : "BEL",
  "name" : {
    "firstName" : "Guillaume",
    "lastName" : "LAMPERTZ",
    "fullName" : "LAMPERTZ, Guillaume"
  },
  "gender" : "MALE",
  "hand" : "RIGHT",
  "birthDay" : {
    "y" : 1993,
    "m" : 3,
    "d" : 13
  }
}, {
  "uid" : "33817",
  "licenseId" : "06091997001",
  "country" : "BEL",
  "name" : {
    "firstName" : "Simon",
    "lastName" : "LAPIN",
    "fullName" : "LAPIN, Simon"
  },
  "gender" : "MALE",
  "hand" : "LEFT",
  "birthDay" : {
    "y" : 1997,
    "m" : 9,
    "d" : 6
  }
}, {
  "uid" : "30837",
  "licenseId" : "30041996003",
  "country" : "BEL",
  "name" : {
    "firstName" : "Violette",
    "lastName" : "LEBRUN",
    "fullName" : "LEBRUN, Violette"
  },
  "gender" : "FEMALE",
  "hand" : "RIGHT",
  "birthDay" : {
    "y" : 1996,
    "m" : 4,
    "d" : 30
  }
}, {
  "uid" : "17123",
  "licenseId" : "19051976001",
  "country" : "BEL",
  "name" : {
    "firstName" : "Benoit",
    "lastName" : "LECLERCQ",
    "fullName" : "LECLERCQ, Benoit"
  },
  "gender" : "MALE",
  "hand" : null,
  "birthDay" : {
    "y" : 1976,
    "m" : 5,
    "d" : 19
  }
}, {
  "uid" : "19830",
  "licenseId" : "10101991002",
  "country" : "BEL",
  "name" : {
    "firstName" : "Hans Joachim",
    "lastName" : "LECOCQ",
    "fullName" : "LECOCQ, Hans Joachim"
  },
  "gender" : "MALE",
  "hand" : "LEFT",
  "birthDay" : {
    "y" : 1991,
    "m" : 10,
    "d" : 10
  }
}, {
  "uid" : "24529",
  "licenseId" : "19051992002",
  "country" : "BEL",
  "name" : {
    "firstName" : "Valentin",
    "lastName" : "LEGRAIN",
    "fullName" : "LEGRAIN, Valentin"
  },
  "gender" : "MALE",
  "hand" : "RIGHT",
  "birthDay" : {
    "y" : 1992,
    "m" : 5,
    "d" : 19
  }
}, {
  "uid" : "28257",
  "licenseId" : "14121993001",
  "country" : "BEL",
  "name" : {
    "firstName" : "Guillaume",
    "lastName" : "LEMAIGRE",
    "fullName" : "LEMAIGRE, Guillaume"
  },
  "gender" : "MALE",
  "hand" : "RIGHT",
  "birthDay" : {
    "y" : 1993,
    "m" : 12,
    "d" : 14
  }
}, {
  "uid" : "17346",
  "licenseId" : "23081988004",
  "country" : "BEL",
  "name" : {
    "firstName" : "Nathan",
    "lastName" : "LHERMITTE",
    "fullName" : "LHERMITTE, Nathan"
  },
  "gender" : "MALE",
  "hand" : null,
  "birthDay" : {
    "y" : 1988,
    "m" : 8,
    "d" : 23
  }
}, {
  "uid" : "25099",
  "licenseId" : "20121993002",
  "country" : "BEL",
  "name" : {
    "firstName" : "Timothe",
    "lastName" : "LIEGE",
    "fullName" : "LIEGE, Timothe"
  },
  "gender" : "MALE",
  "hand" : "RIGHT",
  "birthDay" : {
    "y" : 1993,
    "m" : 12,
    "d" : 20
  }
}, {
  "uid" : "17289",
  "licenseId" : "06071989002",
  "country" : "BEL",
  "name" : {
    "firstName" : "Eva",
    "lastName" : "LIEVENS",
    "fullName" : "LIEVENS, Eva"
  },
  "gender" : "FEMALE",
  "hand" : null,
  "birthDay" : {
    "y" : 1989,
    "m" : 7,
    "d" : 6
  }
}, {
  "uid" : "29893",
  "licenseId" : "31011993001",
  "country" : "BEL",
  "name" : {
    "firstName" : "Joram",
    "lastName" : "MAES",
    "fullName" : "MAES, Joram"
  },
  "gender" : "MALE",
  "hand" : "LEFT",
  "birthDay" : {
    "y" : 1993,
    "m" : 1,
    "d" : 31
  }
}, {
  "uid" : "14485",
  "licenseId" : "08051979000",
  "country" : "BEL",
  "name" : {
    "firstName" : "Alexandre",
    "lastName" : "MAHIEU",
    "fullName" : "MAHIEU, Alexandre"
  },
  "gender" : "MALE",
  "hand" : null,
  "birthDay" : {
    "y" : 1979,
    "m" : 5,
    "d" : 8
  }
}, {
  "uid" : "19667",
  "licenseId" : "11061983003",
  "country" : "BEL",
  "name" : {
    "firstName" : "Vincent",
    "lastName" : "MAHY",
    "fullName" : "MAHY, Vincent"
  },
  "gender" : "MALE",
  "hand" : null,
  "birthDay" : {
    "y" : 1983,
    "m" : 6,
    "d" : 11
  }
}, {
  "uid" : "12386",
  "licenseId" : "25111988000",
  "country" : "BEL",
  "name" : {
    "firstName" : "Aurelien",
    "lastName" : "MARCHAND",
    "fullName" : "MARCHAND, Aurelien"
  },
  "gender" : "MALE",
  "hand" : "RIGHT",
  "birthDay" : {
    "y" : 1988,
    "m" : 11,
    "d" : 25
  }
}, {
  "uid" : "31749",
  "licenseId" : "10101996000",
  "country" : "BEL",
  "name" : {
    "firstName" : "Alexis",
    "lastName" : "MARONET",
    "fullName" : "MARONET, Alexis"
  },
  "gender" : "MALE",
  "hand" : "RIGHT",
  "birthDay" : {
    "y" : 1996,
    "m" : 10,
    "d" : 10
  }
}, {
  "uid" : "42335",
  "licenseId" : null,
  "country" : "BEL",
  "name" : {
    "firstName" : "Andea",
    "lastName" : "MARONET",
    "fullName" : "MARONET, Andea"
  },
  "gender" : null,
  "hand" : null,
  "birthDay" : {
    "y" : 2000,
    "m" : 10,
    "d" : 25
  }
}, {
  "uid" : "32909",
  "licenseId" : "11081997000",
  "country" : "BEL",
  "name" : {
    "firstName" : "Pierre Antoine",
    "lastName" : "MATERNE",
    "fullName" : "MATERNE, Pierre Antoine"
  },
  "gender" : "MALE",
  "hand" : "LEFT",
  "birthDay" : {
    "y" : 1997,
    "m" : 8,
    "d" : 11
  }
}, {
  "uid" : "1759",
  "licenseId" : "06021987001",
  "country" : "BEL",
  "name" : {
    "firstName" : "Thomas",
    "lastName" : "MEMURLIN",
    "fullName" : "MEMURLIN, Thomas"
  },
  "gender" : "MALE",
  "hand" : null,
  "birthDay" : {
    "y" : 1987,
    "m" : 2,
    "d" : 6
  }
}, {
  "uid" : "31934",
  "licenseId" : "21011994002",
  "country" : "BEL",
  "name" : {
    "firstName" : "Frederic",
    "lastName" : "MESTDAGH",
    "fullName" : "MESTDAGH, Frederic"
  },
  "gender" : "MALE",
  "hand" : "RIGHT",
  "birthDay" : {
    "y" : 1994,
    "m" : 1,
    "d" : 21
  }
}, {
  "uid" : "1761",
  "licenseId" : "26061985001",
  "country" : "BEL",
  "name" : {
    "firstName" : "Arnaud",
    "lastName" : "MISTIAEN",
    "fullName" : "MISTIAEN, Arnaud"
  },
  "gender" : "MALE",
  "hand" : null,
  "birthDay" : {
    "y" : 1985,
    "m" : 6,
    "d" : 26
  }
}, {
  "uid" : "1762",
  "licenseId" : "19051985000",
  "country" : "BEL",
  "name" : {
    "firstName" : "Jens",
    "lastName" : "MOENS",
    "fullName" : "MOENS, Jens"
  },
  "gender" : "MALE",
  "hand" : null,
  "birthDay" : {
    "y" : 1985,
    "m" : 5,
    "d" : 19
  }
}, {
  "uid" : "34265",
  "licenseId" : "27011996004",
  "country" : "BEL",
  "name" : {
    "firstName" : "Alexandre",
    "lastName" : "MORTIER",
    "fullName" : "MORTIER, Alexandre"
  },
  "gender" : "MALE",
  "hand" : "RIGHT",
  "birthDay" : {
    "y" : 1996,
    "m" : 1,
    "d" : 27
  }
}, {
  "uid" : "41826",
  "licenseId" : null,
  "country" : "BEL",
  "name" : {
    "firstName" : "Lucas",
    "lastName" : "MOTTIAT",
    "fullName" : "MOTTIAT, Lucas"
  },
  "gender" : null,
  "hand" : null,
  "birthDay" : {
    "y" : 1999,
    "m" : 4,
    "d" : 14
  }
}, {
  "uid" : "28009",
  "licenseId" : "15121994001",
  "country" : "BEL",
  "name" : {
    "firstName" : "Paulina",
    "lastName" : "MURRATH",
    "fullName" : "MURRATH, Paulina"
  },
  "gender" : "FEMALE",
  "hand" : "RIGHT",
  "birthDay" : {
    "y" : 1994,
    "m" : 12,
    "d" : 15
  }
}, {
  "uid" : "17306",
  "licenseId" : "02021976000",
  "country" : "BEL",
  "name" : {
    "firstName" : "Reindert",
    "lastName" : "NACHTERGAELE",
    "fullName" : "NACHTERGAELE, Reindert"
  },
  "gender" : "MALE",
  "hand" : "LEFT",
  "birthDay" : {
    "y" : 1976,
    "m" : 2,
    "d" : 2
  }
}, {
  "uid" : "21784",
  "licenseId" : "30051991001",
  "country" : "BEL",
  "name" : {
    "firstName" : "Mathias",
    "lastName" : "NAGYPAL",
    "fullName" : "NAGYPAL, Mathias"
  },
  "gender" : "MALE",
  "hand" : "RIGHT",
  "birthDay" : {
    "y" : 1991,
    "m" : 5,
    "d" : 30
  }
}, {
  "uid" : "28198",
  "licenseId" : "12111995000",
  "country" : "BEL",
  "name" : {
    "firstName" : "Miguel",
    "lastName" : "NAVAS",
    "fullName" : "NAVAS, Miguel"
  },
  "gender" : "MALE",
  "hand" : "RIGHT",
  "birthDay" : {
    "y" : 1995,
    "m" : 11,
    "d" : 12
  }
}, {
  "uid" : "40305",
  "licenseId" : "28111999001",
  "country" : "BEL",
  "name" : {
    "firstName" : "Timothy",
    "lastName" : "NAVAS",
    "fullName" : "NAVAS, Timothy"
  },
  "gender" : "MALE",
  "hand" : "LEFT",
  "birthDay" : {
    "y" : 1999,
    "m" : 11,
    "d" : 28
  }
}, {
  "uid" : "33836",
  "licenseId" : "30121996001",
  "country" : "BEL",
  "name" : {
    "firstName" : "Guillaume",
    "lastName" : "NOEL",
    "fullName" : "NOEL, Guillaume"
  },
  "gender" : "MALE",
  "hand" : "RIGHT",
  "birthDay" : {
    "y" : 1996,
    "m" : 12,
    "d" : 30
  }
}, {
  "uid" : "19826",
  "licenseId" : "14021989003",
  "country" : "BEL",
  "name" : {
    "firstName" : "Olivier",
    "lastName" : "NOTTE",
    "fullName" : "NOTTE, Olivier"
  },
  "gender" : "MALE",
  "hand" : "RIGHT",
  "birthDay" : {
    "y" : 1989,
    "m" : 2,
    "d" : 14
  }
}, {
  "uid" : "15979",
  "licenseId" : "18081989001",
  "country" : "BEL",
  "name" : {
    "firstName" : "Thibault",
    "lastName" : "OOSTERBOSCH",
    "fullName" : "OOSTERBOSCH, Thibault"
  },
  "gender" : "MALE",
  "hand" : "RIGHT",
  "birthDay" : {
    "y" : 1989,
    "m" : 8,
    "d" : 18
  }
}, {
  "uid" : "27978",
  "licenseId" : "19051993004",
  "country" : "BEL",
  "name" : {
    "firstName" : "Olivier",
    "lastName" : "PARISSE",
    "fullName" : "PARISSE, Olivier"
  },
  "gender" : "MALE",
  "hand" : "RIGHT",
  "birthDay" : {
    "y" : 1993,
    "m" : 5,
    "d" : 19
  }
}, {
  "uid" : "28199",
  "licenseId" : "03081995002",
  "country" : "BEL",
  "name" : {
    "firstName" : "Clement",
    "lastName" : "PARMENTIER",
    "fullName" : "PARMENTIER, Clement"
  },
  "gender" : "MALE",
  "hand" : "RIGHT",
  "birthDay" : {
    "y" : 1995,
    "m" : 8,
    "d" : 3
  }
}, {
  "uid" : "35829",
  "licenseId" : "25011996003",
  "country" : "BEL",
  "name" : {
    "firstName" : "Kamiel",
    "lastName" : "PEETERS",
    "fullName" : "PEETERS, Kamiel"
  },
  "gender" : "MALE",
  "hand" : "RIGHT",
  "birthDay" : {
    "y" : 1996,
    "m" : 1,
    "d" : 25
  }
}, {
  "uid" : "29890",
  "licenseId" : "02121994000",
  "country" : "BEL",
  "name" : {
    "firstName" : "Jules",
    "lastName" : "PHILIPPE",
    "fullName" : "PHILIPPE, Jules"
  },
  "gender" : "MALE",
  "hand" : "RIGHT",
  "birthDay" : {
    "y" : 1994,
    "m" : 12,
    "d" : 2
  }
}, {
  "uid" : "1767",
  "licenseId" : "11121981001",
  "country" : "BEL",
  "name" : {
    "firstName" : "Luc",
    "lastName" : "PICHON",
    "fullName" : "PICHON, Luc"
  },
  "gender" : "MALE",
  "hand" : null,
  "birthDay" : {
    "y" : 1981,
    "m" : 12,
    "d" : 11
  }
}, {
  "uid" : "1768",
  "licenseId" : "21081977000",
  "country" : "BEL",
  "name" : {
    "firstName" : "Marc",
    "lastName" : "PICHON",
    "fullName" : "PICHON, Marc"
  },
  "gender" : "MALE",
  "hand" : null,
  "birthDay" : {
    "y" : 1977,
    "m" : 8,
    "d" : 21
  }
}, {
  "uid" : "17322",
  "licenseId" : "17071992000",
  "country" : "BEL",
  "name" : {
    "firstName" : "Harry",
    "lastName" : "PINSON",
    "fullName" : "PINSON, Harry"
  },
  "gender" : "MALE",
  "hand" : "RIGHT",
  "birthDay" : {
    "y" : 1992,
    "m" : 7,
    "d" : 17
  }
}, {
  "uid" : "10913",
  "licenseId" : "13061967000",
  "country" : "BEL",
  "name" : {
    "firstName" : "Renaud",
    "lastName" : "POIZAT",
    "fullName" : "POIZAT, Renaud"
  },
  "gender" : "MALE",
  "hand" : "RIGHT",
  "birthDay" : {
    "y" : 1967,
    "m" : 6,
    "d" : 13
  }
}, {
  "uid" : "39069",
  "licenseId" : "28121998004",
  "country" : "BEL",
  "name" : {
    "firstName" : "Nicolas",
    "lastName" : "PONCIN",
    "fullName" : "PONCIN, Nicolas"
  },
  "gender" : "MALE",
  "hand" : "RIGHT",
  "birthDay" : {
    "y" : 1998,
    "m" : 12,
    "d" : 28
  }
}, {
  "uid" : "26771",
  "licenseId" : "29011994001",
  "country" : "BEL",
  "name" : {
    "firstName" : "Robin",
    "lastName" : "PONNET",
    "fullName" : "PONNET, Robin"
  },
  "gender" : "MALE",
  "hand" : "RIGHT",
  "birthDay" : {
    "y" : 1994,
    "m" : 1,
    "d" : 29
  }
}, {
  "uid" : "29896",
  "licenseId" : "29061995003",
  "country" : "BEL",
  "name" : {
    "firstName" : "Martin",
    "lastName" : "PRAILE",
    "fullName" : "PRAILE, Martin"
  },
  "gender" : "MALE",
  "hand" : "RIGHT",
  "birthDay" : {
    "y" : 1995,
    "m" : 6,
    "d" : 29
  }
}, {
  "uid" : "42626",
  "licenseId" : null,
  "country" : "BEL",
  "name" : {
    "firstName" : "Mael",
    "lastName" : "PROSSE",
    "fullName" : "PROSSE, Mael"
  },
  "gender" : null,
  "hand" : null,
  "birthDay" : {
    "y" : 2001,
    "m" : 3,
    "d" : 20
  }
}, {
  "uid" : "28256",
  "licenseId" : "08101993003",
  "country" : "BEL",
  "name" : {
    "firstName" : "Kevin",
    "lastName" : "RADELET",
    "fullName" : "RADELET, Kevin"
  },
  "gender" : "MALE",
  "hand" : "RIGHT",
  "birthDay" : {
    "y" : 1993,
    "m" : 10,
    "d" : 8
  }
}, {
  "uid" : "38768",
  "licenseId" : "20041998004",
  "country" : "BEL",
  "name" : {
    "firstName" : "Bastien",
    "lastName" : "RAPPE",
    "fullName" : "RAPPE, Bastien"
  },
  "gender" : "MALE",
  "hand" : "RIGHT",
  "birthDay" : {
    "y" : 1998,
    "m" : 4,
    "d" : 20
  }
}, {
  "uid" : "23889",
  "licenseId" : "26031992002",
  "country" : "BEL",
  "name" : {
    "firstName" : "Gaspard",
    "lastName" : "REGIBEAU",
    "fullName" : "REGIBEAU, Gaspard"
  },
  "gender" : "MALE",
  "hand" : "RIGHT",
  "birthDay" : {
    "y" : 1992,
    "m" : 3,
    "d" : 26
  }
}, {
  "uid" : "29892",
  "licenseId" : "06101994003",
  "country" : "BEL",
  "name" : {
    "firstName" : "Gregoire",
    "lastName" : "REGINSTER",
    "fullName" : "REGINSTER, Gregoire"
  },
  "gender" : "MALE",
  "hand" : "RIGHT",
  "birthDay" : {
    "y" : 1994,
    "m" : 10,
    "d" : 6
  }
}, {
  "uid" : "28117",
  "licenseId" : "14051994002",
  "country" : "BEL",
  "name" : {
    "firstName" : "Samuel",
    "lastName" : "REYNAERT",
    "fullName" : "REYNAERT, Samuel"
  },
  "gender" : "MALE",
  "hand" : "RIGHT",
  "birthDay" : {
    "y" : 1994,
    "m" : 5,
    "d" : 14
  }
}, {
  "uid" : "18578",
  "licenseId" : "10111971000",
  "country" : "BEL",
  "name" : {
    "firstName" : "Christophe",
    "lastName" : "ROOSE",
    "fullName" : "ROOSE, Christophe"
  },
  "gender" : "MALE",
  "hand" : "LEFT",
  "birthDay" : {
    "y" : 1971,
    "m" : 11,
    "d" : 10
  }
}, {
  "uid" : "35830",
  "licenseId" : "13011998001",
  "country" : "BEL",
  "name" : {
    "firstName" : "Samuel",
    "lastName" : "ROUDBAR",
    "fullName" : "ROUDBAR, Samuel"
  },
  "gender" : "MALE",
  "hand" : "RIGHT",
  "birthDay" : {
    "y" : 1998,
    "m" : 1,
    "d" : 13
  }
}, {
  "uid" : "41825",
  "licenseId" : null,
  "country" : "BEL",
  "name" : {
    "firstName" : "Sam",
    "lastName" : "RUYSSEVELDT",
    "fullName" : "RUYSSEVELDT, Sam"
  },
  "gender" : null,
  "hand" : null,
  "birthDay" : {
    "y" : 1999,
    "m" : 6,
    "d" : 9
  }
}, {
  "uid" : "1771",
  "licenseId" : "17031985001",
  "country" : "BEL",
  "name" : {
    "firstName" : "Alexandra",
    "lastName" : "SAITTA",
    "fullName" : "SAITTA, Alexandra"
  },
  "gender" : "FEMALE",
  "hand" : "RIGHT",
  "birthDay" : {
    "y" : 1985,
    "m" : 3,
    "d" : 17
  }
}, {
  "uid" : "14617",
  "licenseId" : "23051986005",
  "country" : "BEL",
  "name" : {
    "firstName" : "Sebastien",
    "lastName" : "SANTARELLI",
    "fullName" : "SANTARELLI, Sebastien"
  },
  "gender" : "MALE",
  "hand" : "RIGHT",
  "birthDay" : {
    "y" : 1986,
    "m" : 5,
    "d" : 23
  }
}, {
  "uid" : "21917",
  "licenseId" : "26011990002",
  "country" : "BEL",
  "name" : {
    "firstName" : "Valentin",
    "lastName" : "SANTARELLI",
    "fullName" : "SANTARELLI, Valentin"
  },
  "gender" : "MALE",
  "hand" : null,
  "birthDay" : {
    "y" : 1990,
    "m" : 1,
    "d" : 26
  }
}, {
  "uid" : "18976",
  "licenseId" : "28051963000",
  "country" : "BEL",
  "name" : {
    "firstName" : "Els",
    "lastName" : "SCHEPENS",
    "fullName" : "SCHEPENS, Els"
  },
  "gender" : "FEMALE",
  "hand" : "RIGHT",
  "birthDay" : {
    "y" : 1963,
    "m" : 5,
    "d" : 28
  }
}, {
  "uid" : "1772",
  "licenseId" : "05071977000",
  "country" : "BEL",
  "name" : {
    "firstName" : "Nele",
    "lastName" : "SCHOUTERDEN",
    "fullName" : "SCHOUTERDEN, Nele"
  },
  "gender" : "FEMALE",
  "hand" : null,
  "birthDay" : {
    "y" : 1977,
    "m" : 7,
    "d" : 5
  }
}, {
  "uid" : "12385",
  "licenseId" : "17031988000",
  "country" : "BEL",
  "name" : {
    "firstName" : "Thomas",
    "lastName" : "SEDRAN",
    "fullName" : "SEDRAN, Thomas"
  },
  "gender" : "MALE",
  "hand" : null,
  "birthDay" : {
    "y" : 1988,
    "m" : 3,
    "d" : 17
  }
}, {
  "uid" : "39090",
  "licenseId" : "23031998002",
  "country" : "BEL",
  "name" : {
    "firstName" : "Charlotte",
    "lastName" : "SERMEUS",
    "fullName" : "SERMEUS, Charlotte"
  },
  "gender" : "FEMALE",
  "hand" : "RIGHT",
  "birthDay" : {
    "y" : 1998,
    "m" : 3,
    "d" : 23
  }
}, {
  "uid" : "17323",
  "licenseId" : "12041991000",
  "country" : "BEL",
  "name" : {
    "firstName" : "Georges",
    "lastName" : "SHVARTSMAN",
    "fullName" : "SHVARTSMAN, Georges"
  },
  "gender" : "MALE",
  "hand" : "RIGHT",
  "birthDay" : {
    "y" : 1991,
    "m" : 4,
    "d" : 12
  }
}, {
  "uid" : "28118",
  "licenseId" : "05081993007",
  "country" : "BEL",
  "name" : {
    "firstName" : "Barbara",
    "lastName" : "SIMOEN",
    "fullName" : "SIMOEN, Barbara"
  },
  "gender" : "FEMALE",
  "hand" : "RIGHT",
  "birthDay" : {
    "y" : 1993,
    "m" : 8,
    "d" : 5
  }
}, {
  "uid" : "10859",
  "licenseId" : "07121989000",
  "country" : "BEL",
  "name" : {
    "firstName" : "Frederik",
    "lastName" : "SIMOEN",
    "fullName" : "SIMOEN, Frederik"
  },
  "gender" : "MALE",
  "hand" : "RIGHT",
  "birthDay" : {
    "y" : 1989,
    "m" : 12,
    "d" : 7
  }
}, {
  "uid" : "31932",
  "licenseId" : "07051995001",
  "country" : "BEL",
  "name" : {
    "firstName" : "Kiran",
    "lastName" : "SINIMALE",
    "fullName" : "SINIMALE, Kiran"
  },
  "gender" : "FEMALE",
  "hand" : "RIGHT",
  "birthDay" : {
    "y" : 1995,
    "m" : 5,
    "d" : 7
  }
}, {
  "uid" : "1775",
  "licenseId" : "07081987000",
  "country" : "BEL",
  "name" : {
    "firstName" : "Bo",
    "lastName" : "SMET",
    "fullName" : "SMET, Bo"
  },
  "gender" : "MALE",
  "hand" : null,
  "birthDay" : {
    "y" : 1987,
    "m" : 8,
    "d" : 7
  }
}, {
  "uid" : "7367",
  "licenseId" : "11071976000",
  "country" : "BEL",
  "name" : {
    "firstName" : "Diego",
    "lastName" : "SOUDAN",
    "fullName" : "SOUDAN, Diego"
  },
  "gender" : "MALE",
  "hand" : "RIGHT",
  "birthDay" : {
    "y" : 1976,
    "m" : 7,
    "d" : 11
  }
}, {
  "uid" : "6726",
  "licenseId" : "19061969000",
  "country" : "BEL",
  "name" : {
    "firstName" : "Elisabeth",
    "lastName" : "SPILMAN",
    "fullName" : "SPILMAN, Elisabeth"
  },
  "gender" : "FEMALE",
  "hand" : null,
  "birthDay" : {
    "y" : 1969,
    "m" : 6,
    "d" : 19
  }
}, {
  "uid" : "31746",
  "licenseId" : "12061997000",
  "country" : "BEL",
  "name" : {
    "firstName" : "Frans",
    "lastName" : "SWENNEN",
    "fullName" : "SWENNEN, Frans"
  },
  "gender" : "MALE",
  "hand" : "LEFT",
  "birthDay" : {
    "y" : 1997,
    "m" : 6,
    "d" : 12
  }
}, {
  "uid" : "26815",
  "licenseId" : "26121992001",
  "country" : "BEL",
  "name" : {
    "firstName" : "Annick",
    "lastName" : "SWINNE",
    "fullName" : "SWINNE, Annick"
  },
  "gender" : "FEMALE",
  "hand" : "RIGHT",
  "birthDay" : {
    "y" : 1992,
    "m" : 12,
    "d" : 26
  }
}, {
  "uid" : "27984",
  "licenseId" : "08101994004",
  "country" : "BEL",
  "name" : {
    "firstName" : "Alan",
    "lastName" : "TABURY",
    "fullName" : "TABURY, Alan"
  },
  "gender" : "MALE",
  "hand" : "RIGHT",
  "birthDay" : {
    "y" : 1994,
    "m" : 10,
    "d" : 8
  }
}, {
  "uid" : "26363",
  "licenseId" : "10041992004",
  "country" : "BEL",
  "name" : {
    "firstName" : "Florian",
    "lastName" : "THIRY",
    "fullName" : "THIRY, Florian"
  },
  "gender" : "MALE",
  "hand" : "RIGHT",
  "birthDay" : {
    "y" : 1992,
    "m" : 4,
    "d" : 10
  }
}, {
  "uid" : "30632",
  "licenseId" : "14061995003",
  "country" : "BEL",
  "name" : {
    "firstName" : "Galiene",
    "lastName" : "THOELEN",
    "fullName" : "THOELEN, Galiene"
  },
  "gender" : "FEMALE",
  "hand" : "RIGHT",
  "birthDay" : {
    "y" : 1995,
    "m" : 6,
    "d" : 14
  }
}, {
  "uid" : "31750",
  "licenseId" : "13011996004",
  "country" : "BEL",
  "name" : {
    "firstName" : "Nathan",
    "lastName" : "TIMMERMANS",
    "fullName" : "TIMMERMANS, Nathan"
  },
  "gender" : "MALE",
  "hand" : "RIGHT",
  "birthDay" : {
    "y" : 1996,
    "m" : 1,
    "d" : 13
  }
}, {
  "uid" : "34255",
  "licenseId" : "01091999001",
  "country" : "BEL",
  "name" : {
    "firstName" : "Karel",
    "lastName" : "TOCH",
    "fullName" : "TOCH, Karel"
  },
  "gender" : "MALE",
  "hand" : "RIGHT",
  "birthDay" : {
    "y" : 1999,
    "m" : 9,
    "d" : 1
  }
}, {
  "uid" : "1777",
  "licenseId" : "06051985003",
  "country" : "BEL",
  "name" : {
    "firstName" : "Frederiek",
    "lastName" : "TROUBLEYN",
    "fullName" : "TROUBLEYN, Frederiek"
  },
  "gender" : "MALE",
  "hand" : "RIGHT",
  "birthDay" : {
    "y" : 1985,
    "m" : 5,
    "d" : 6
  }
}, {
  "uid" : "20562",
  "licenseId" : "03091975001",
  "country" : "BEL",
  "name" : {
    "firstName" : "Antoine Georges",
    "lastName" : "UBAGHS",
    "fullName" : "UBAGHS, Antoine Georges"
  },
  "gender" : "MALE",
  "hand" : "RIGHT",
  "birthDay" : {
    "y" : 1975,
    "m" : 9,
    "d" : 3
  }
}, {
  "uid" : "39148",
  "licenseId" : "26031998009",
  "country" : "BEL",
  "name" : {
    "firstName" : "Elise",
    "lastName" : "VAEREMANS",
    "fullName" : "VAEREMANS, Elise"
  },
  "gender" : "FEMALE",
  "hand" : "LEFT",
  "birthDay" : {
    "y" : 1998,
    "m" : 3,
    "d" : 26
  }
}, {
  "uid" : "39091",
  "licenseId" : "16021997002",
  "country" : "BEL",
  "name" : {
    "firstName" : "Arno",
    "lastName" : "VAN BREUSEGHEM",
    "fullName" : "VAN BREUSEGHEM, Arno"
  },
  "gender" : "MALE",
  "hand" : "RIGHT",
  "birthDay" : {
    "y" : 1997,
    "m" : 2,
    "d" : 16
  }
}, {
  "uid" : "37860",
  "licenseId" : "28051998006",
  "country" : "BEL",
  "name" : {
    "firstName" : "Stef",
    "lastName" : "VAN CAMPENHOUT",
    "fullName" : "VAN CAMPENHOUT, Stef"
  },
  "gender" : "MALE",
  "hand" : "RIGHT",
  "birthDay" : {
    "y" : 1998,
    "m" : 5,
    "d" : 28
  }
}, {
  "uid" : "27117",
  "licenseId" : "10031984009",
  "country" : "BEL",
  "name" : {
    "firstName" : "Robrecht",
    "lastName" : "VAN CLEEMPUT",
    "fullName" : "VAN CLEEMPUT, Robrecht"
  },
  "gender" : "MALE",
  "hand" : "RIGHT",
  "birthDay" : {
    "y" : 1984,
    "m" : 3,
    "d" : 10
  }
}, {
  "uid" : "17417",
  "licenseId" : "22051970002",
  "country" : "BEL",
  "name" : {
    "firstName" : "Gert",
    "lastName" : "VAN CONKELBERGE",
    "fullName" : "VAN CONKELBERGE, Gert"
  },
  "gender" : "MALE",
  "hand" : "RIGHT",
  "birthDay" : {
    "y" : 1970,
    "m" : 5,
    "d" : 22
  }
}, {
  "uid" : "12173",
  "licenseId" : "06101963000",
  "country" : "BEL",
  "name" : {
    "firstName" : "Catherine",
    "lastName" : "VAN DEN BRULLE",
    "fullName" : "VAN DEN BRULLE, Catherine"
  },
  "gender" : "FEMALE",
  "hand" : "RIGHT",
  "birthDay" : {
    "y" : 1963,
    "m" : 10,
    "d" : 6
  }
}, {
  "uid" : "9595",
  "licenseId" : "29041981001",
  "country" : "BEL",
  "name" : {
    "firstName" : "Frederik",
    "lastName" : "VAN DORMAEL",
    "fullName" : "VAN DORMAEL, Frederik"
  },
  "gender" : "MALE",
  "hand" : "RIGHT",
  "birthDay" : {
    "y" : 1981,
    "m" : 4,
    "d" : 29
  }
}, {
  "uid" : "11988",
  "licenseId" : "20091989000",
  "country" : "BEL",
  "name" : {
    "firstName" : "Melanie",
    "lastName" : "VAN DORPE",
    "fullName" : "VAN DORPE, Melanie"
  },
  "gender" : "FEMALE",
  "hand" : "RIGHT",
  "birthDay" : {
    "y" : 1989,
    "m" : 9,
    "d" : 20
  }
}, {
  "uid" : "34256",
  "licenseId" : "08111997002",
  "country" : "BEL",
  "name" : {
    "firstName" : "Egon",
    "lastName" : "VAN DURME",
    "fullName" : "VAN DURME, Egon"
  },
  "gender" : "MALE",
  "hand" : "RIGHT",
  "birthDay" : {
    "y" : 1997,
    "m" : 11,
    "d" : 8
  }
}, {
  "uid" : "23563",
  "licenseId" : "13101991002",
  "country" : "BEL",
  "name" : {
    "firstName" : "Mathias",
    "lastName" : "VAN ENGELAND",
    "fullName" : "VAN ENGELAND, Mathias"
  },
  "gender" : "MALE",
  "hand" : "RIGHT",
  "birthDay" : {
    "y" : 1991,
    "m" : 10,
    "d" : 13
  }
}, {
  "uid" : "33819",
  "licenseId" : "16081996005",
  "country" : "BEL",
  "name" : {
    "firstName" : "Sander",
    "lastName" : "VAN GIJSEL",
    "fullName" : "VAN GIJSEL, Sander"
  },
  "gender" : "MALE",
  "hand" : "LEFT",
  "birthDay" : {
    "y" : 1996,
    "m" : 8,
    "d" : 16
  }
}, {
  "uid" : "23525",
  "licenseId" : "19061990004",
  "country" : "BEL",
  "name" : {
    "firstName" : "Benjamin",
    "lastName" : "VAN HOEY",
    "fullName" : "VAN HOEY, Benjamin"
  },
  "gender" : "MALE",
  "hand" : "RIGHT",
  "birthDay" : {
    "y" : 1990,
    "m" : 6,
    "d" : 19
  }
}, {
  "uid" : "12186",
  "licenseId" : "09011986004",
  "country" : "BEL",
  "name" : {
    "firstName" : "Cedric",
    "lastName" : "VAN HOLSBEKE",
    "fullName" : "VAN HOLSBEKE, Cedric"
  },
  "gender" : "MALE",
  "hand" : "RIGHT",
  "birthDay" : {
    "y" : 1986,
    "m" : 1,
    "d" : 9
  }
}, {
  "uid" : "10861",
  "licenseId" : "19011988002",
  "country" : "BEL",
  "name" : {
    "firstName" : "Seppe",
    "lastName" : "VAN HOLSBEKE",
    "fullName" : "VAN HOLSBEKE, Seppe"
  },
  "gender" : "MALE",
  "hand" : "RIGHT",
  "birthDay" : {
    "y" : 1988,
    "m" : 1,
    "d" : 19
  }
}, {
  "uid" : "17290",
  "licenseId" : "15101988000",
  "country" : "BEL",
  "name" : {
    "firstName" : "Simon",
    "lastName" : "VAN HOOREN",
    "fullName" : "VAN HOOREN, Simon"
  },
  "gender" : "MALE",
  "hand" : "RIGHT",
  "birthDay" : {
    "y" : 1988,
    "m" : 10,
    "d" : 15
  }
}, {
  "uid" : "21686",
  "licenseId" : "20061990002",
  "country" : "BEL",
  "name" : {
    "firstName" : "Romain",
    "lastName" : "VAN HULLE",
    "fullName" : "VAN HULLE, Romain"
  },
  "gender" : "MALE",
  "hand" : "RIGHT",
  "birthDay" : {
    "y" : 1990,
    "m" : 6,
    "d" : 20
  }
}, {
  "uid" : "10118",
  "licenseId" : "07031977005",
  "country" : "BEL",
  "name" : {
    "firstName" : "Yoeri",
    "lastName" : "VAN LAECKE",
    "fullName" : "VAN LAECKE, Yoeri"
  },
  "gender" : "MALE",
  "hand" : "RIGHT",
  "birthDay" : {
    "y" : 1977,
    "m" : 3,
    "d" : 7
  }
}, {
  "uid" : "42198",
  "licenseId" : null,
  "country" : "BEL",
  "name" : {
    "firstName" : "Nan",
    "lastName" : "VAN RIJCKEGHEM",
    "fullName" : "VAN RIJCKEGHEM, Nan"
  },
  "gender" : "FEMALE",
  "hand" : "RIGHT",
  "birthDay" : {
    "y" : 2001,
    "m" : 4,
    "d" : 4
  }
}, {
  "uid" : "10194",
  "licenseId" : "29031985003",
  "country" : "BEL",
  "name" : {
    "firstName" : "Simon",
    "lastName" : "VAN WAMBEKE",
    "fullName" : "VAN WAMBEKE, Simon"
  },
  "gender" : "MALE",
  "hand" : "RIGHT",
  "birthDay" : {
    "y" : 1985,
    "m" : 3,
    "d" : 29
  }
}, {
  "uid" : "16581",
  "licenseId" : "28031978002",
  "country" : "BEL",
  "name" : {
    "firstName" : "Kathleen",
    "lastName" : "VANBELLINGHEN",
    "fullName" : "VANBELLINGHEN, Kathleen"
  },
  "gender" : "FEMALE",
  "hand" : "RIGHT",
  "birthDay" : {
    "y" : 1978,
    "m" : 3,
    "d" : 28
  }
}, {
  "uid" : "32683",
  "licenseId" : "07011996007",
  "country" : "BEL",
  "name" : {
    "firstName" : "Linde",
    "lastName" : "VANDECRUYS",
    "fullName" : "VANDECRUYS, Linde"
  },
  "gender" : "FEMALE",
  "hand" : "RIGHT",
  "birthDay" : {
    "y" : 1996,
    "m" : 1,
    "d" : 7
  }
}, {
  "uid" : "29854",
  "licenseId" : "27101994000",
  "country" : "BEL",
  "name" : {
    "firstName" : "Casper",
    "lastName" : "VANDEN BILCKE",
    "fullName" : "VANDEN BILCKE, Casper"
  },
  "gender" : "MALE",
  "hand" : "RIGHT",
  "birthDay" : {
    "y" : 1994,
    "m" : 10,
    "d" : 27
  }
}, {
  "uid" : "23699",
  "licenseId" : "26081994000",
  "country" : "BEL",
  "name" : {
    "firstName" : "Nicolas",
    "lastName" : "VANDER EECKEN",
    "fullName" : "VANDER EECKEN, Nicolas"
  },
  "gender" : "MALE",
  "hand" : "RIGHT",
  "birthDay" : {
    "y" : 1994,
    "m" : 8,
    "d" : 26
  }
}, {
  "uid" : "1785",
  "licenseId" : "23061980000",
  "country" : "BEL",
  "name" : {
    "firstName" : "Jean-Baptiste",
    "lastName" : "VANELSHANDER",
    "fullName" : "VANELSHANDER, Jean-Baptiste"
  },
  "gender" : "MALE",
  "hand" : "RIGHT",
  "birthDay" : {
    "y" : 1980,
    "m" : 6,
    "d" : 23
  }
}, {
  "uid" : "14419",
  "licenseId" : "17111988001",
  "country" : "BEL",
  "name" : {
    "firstName" : "Meven",
    "lastName" : "VANHAMME",
    "fullName" : "VANHAMME, Meven"
  },
  "gender" : "MALE",
  "hand" : "RIGHT",
  "birthDay" : {
    "y" : 1988,
    "m" : 11,
    "d" : 17
  }
}, {
  "uid" : "25876",
  "licenseId" : "11101993001",
  "country" : "BEL",
  "name" : {
    "firstName" : "Fanny",
    "lastName" : "VANHULLE",
    "fullName" : "VANHULLE, Fanny"
  },
  "gender" : "FEMALE",
  "hand" : "RIGHT",
  "birthDay" : {
    "y" : 1993,
    "m" : 10,
    "d" : 11
  }
}, {
  "uid" : "7993",
  "licenseId" : "29051979000",
  "country" : "BEL",
  "name" : {
    "firstName" : "Genevieve",
    "lastName" : "VANHUYSSE",
    "fullName" : "VANHUYSSE, Genevieve"
  },
  "gender" : "FEMALE",
  "hand" : "RIGHT",
  "birthDay" : {
    "y" : 1979,
    "m" : 5,
    "d" : 29
  }
}, {
  "uid" : "36706",
  "licenseId" : "11061997003",
  "country" : "BEL",
  "name" : {
    "firstName" : "Bjarne",
    "lastName" : "VEREECKE",
    "fullName" : "VEREECKE, Bjarne"
  },
  "gender" : "MALE",
  "hand" : "RIGHT",
  "birthDay" : {
    "y" : 1997,
    "m" : 6,
    "d" : 11
  }
}, {
  "uid" : "24683",
  "licenseId" : "26021992005",
  "country" : "BEL",
  "name" : {
    "firstName" : "Nicolas",
    "lastName" : "VERHELLE",
    "fullName" : "VERHELLE, Nicolas"
  },
  "gender" : "MALE",
  "hand" : "LEFT",
  "birthDay" : {
    "y" : 1992,
    "m" : 2,
    "d" : 26
  }
}, {
  "uid" : "33820",
  "licenseId" : "13121996000",
  "country" : "BEL",
  "name" : {
    "firstName" : "Thibault",
    "lastName" : "VERHELLE",
    "fullName" : "VERHELLE, Thibault"
  },
  "gender" : "MALE",
  "hand" : "RIGHT",
  "birthDay" : {
    "y" : 1996,
    "m" : 12,
    "d" : 13
  }
}, {
  "uid" : "1790",
  "licenseId" : "04051985000",
  "country" : "BEL",
  "name" : {
    "firstName" : "Pierre",
    "lastName" : "VERHELST",
    "fullName" : "VERHELST, Pierre"
  },
  "gender" : "MALE",
  "hand" : null,
  "birthDay" : {
    "y" : 1985,
    "m" : 5,
    "d" : 4
  }
}, {
  "uid" : "21789",
  "licenseId" : "02031993001",
  "country" : "BEL",
  "name" : {
    "firstName" : "Loic",
    "lastName" : "VERNIMMEN",
    "fullName" : "VERNIMMEN, Loic"
  },
  "gender" : "MALE",
  "hand" : "RIGHT",
  "birthDay" : {
    "y" : 1993,
    "m" : 3,
    "d" : 2
  }
}, {
  "uid" : "41788",
  "licenseId" : null,
  "country" : "BEL",
  "name" : {
    "firstName" : "Crijn",
    "lastName" : "VERWAAL",
    "fullName" : "VERWAAL, Crijn"
  },
  "gender" : null,
  "hand" : null,
  "birthDay" : {
    "y" : 1999,
    "m" : 7,
    "d" : 14
  }
}, {
  "uid" : "17403",
  "licenseId" : "23091985006",
  "country" : "BEL",
  "name" : {
    "firstName" : "Matthieu",
    "lastName" : "VINCK",
    "fullName" : "VINCK, Matthieu"
  },
  "gender" : "MALE",
  "hand" : "RIGHT",
  "birthDay" : {
    "y" : 1985,
    "m" : 9,
    "d" : 23
  }
}, {
  "uid" : "17309",
  "licenseId" : "29091976001",
  "country" : "BEL",
  "name" : {
    "firstName" : "Dimitri",
    "lastName" : "VIVANE",
    "fullName" : "VIVANE, Dimitri"
  },
  "gender" : "MALE",
  "hand" : null,
  "birthDay" : {
    "y" : 1976,
    "m" : 9,
    "d" : 29
  }
}, {
  "uid" : "26707",
  "licenseId" : "21051991004",
  "country" : "BEL",
  "name" : {
    "firstName" : "Alexandre",
    "lastName" : "VIVIERS",
    "fullName" : "VIVIERS, Alexandre"
  },
  "gender" : "MALE",
  "hand" : "RIGHT",
  "birthDay" : {
    "y" : 1991,
    "m" : 5,
    "d" : 21
  }
}, {
  "uid" : "36446",
  "licenseId" : "04021998003",
  "country" : "BEL",
  "name" : {
    "firstName" : "Ezra",
    "lastName" : "VLEUGELS",
    "fullName" : "VLEUGELS, Ezra"
  },
  "gender" : "FEMALE",
  "hand" : "LEFT",
  "birthDay" : {
    "y" : 1998,
    "m" : 2,
    "d" : 4
  }
}, {
  "uid" : "28197",
  "licenseId" : "29091993001",
  "country" : "BEL",
  "name" : {
    "firstName" : "Michiel",
    "lastName" : "VUYLSTEKE",
    "fullName" : "VUYLSTEKE, Michiel"
  },
  "gender" : "MALE",
  "hand" : "RIGHT",
  "birthDay" : {
    "y" : 1993,
    "m" : 9,
    "d" : 29
  }
}, {
  "uid" : "29898",
  "licenseId" : "23121992001",
  "country" : "BEL",
  "name" : {
    "firstName" : "Sander",
    "lastName" : "WARREYN",
    "fullName" : "WARREYN, Sander"
  },
  "gender" : "MALE",
  "hand" : "RIGHT",
  "birthDay" : {
    "y" : 1992,
    "m" : 12,
    "d" : 23
  }
}, {
  "uid" : "17145",
  "licenseId" : "22041988003",
  "country" : "BEL",
  "name" : {
    "firstName" : "Charlotte",
    "lastName" : "WAXWEILER",
    "fullName" : "WAXWEILER, Charlotte"
  },
  "gender" : "FEMALE",
  "hand" : null,
  "birthDay" : {
    "y" : 1988,
    "m" : 4,
    "d" : 22
  }
}, {
  "uid" : "17146",
  "licenseId" : "28031981000",
  "country" : "BEL",
  "name" : {
    "firstName" : "Sebastien",
    "lastName" : "WETS",
    "fullName" : "WETS, Sebastien"
  },
  "gender" : "MALE",
  "hand" : null,
  "birthDay" : {
    "y" : 1981,
    "m" : 3,
    "d" : 28
  }
}, {
  "uid" : "29897",
  "licenseId" : "28011994002",
  "country" : "BEL",
  "name" : {
    "firstName" : "Stijn",
    "lastName" : "WINDELS",
    "fullName" : "WINDELS, Stijn"
  },
  "gender" : "MALE",
  "hand" : "RIGHT",
  "birthDay" : {
    "y" : 1994,
    "m" : 1,
    "d" : 28
  }
}, {
  "uid" : "21918",
  "licenseId" : "24071990004",
  "country" : "BEL",
  "name" : {
    "firstName" : "Alexandre",
    "lastName" : "WITON",
    "fullName" : "WITON, Alexandre"
  },
  "gender" : "MALE",
  "hand" : "RIGHT",
  "birthDay" : {
    "y" : 1990,
    "m" : 7,
    "d" : 24
  }
}, {
  "uid" : "1792",
  "licenseId" : "04101984000",
  "country" : "BEL",
  "name" : {
    "firstName" : "Marilyne",
    "lastName" : "WOLNY",
    "fullName" : "WOLNY, Marilyne"
  },
  "gender" : "FEMALE",
  "hand" : "RIGHT",
  "birthDay" : {
    "y" : 1984,
    "m" : 10,
    "d" : 4
  }
} ]