[ {
  "uid" : "31218",
  "licenseId" : null,
  "country" : "CIV",
  "name" : {
    "firstName" : "Akmel Gery Valens",
    "lastName" : "BEUGRE",
    "fullName" : "BEUGRE, Akmel Gery Valens"
  },
  "gender" : null,
  "hand" : null,
  "birthDay" : {
    "y" : 1992,
    "m" : 7,
    "d" : 19
  }
}, {
  "uid" : "30891",
  "licenseId" : null,
  "country" : "CIV",
  "name" : {
    "firstName" : "Gbahi Gwladys",
    "lastName" : "SAKOA",
    "fullName" : "SAKOA, Gbahi Gwladys"
  },
  "gender" : null,
  "hand" : null,
  "birthDay" : {
    "y" : 1992,
    "m" : 12,
    "d" : 3
  }
}, {
  "uid" : "37465",
  "licenseId" : null,
  "country" : "CIV",
  "name" : {
    "firstName" : "Hans Calixte De Bre",
    "lastName" : "TIA",
    "fullName" : "TIA, Hans Calixte De Bre"
  },
  "gender" : null,
  "hand" : null,
  "birthDay" : {
    "y" : 1997,
    "m" : 1,
    "d" : 9
  }
} ]