[ {
  "uid" : "35271",
  "licenseId" : null,
  "country" : "SIN",
  "name" : {
    "firstName" : "Kiria Tikanah",
    "lastName" : "ABDUL RAHMAN",
    "fullName" : "ABDUL RAHMAN, Kiria Tikanah"
  },
  "gender" : null,
  "hand" : null,
  "birthDay" : {
    "y" : 2000,
    "m" : 6,
    "d" : 25
  }
}, {
  "uid" : "39008",
  "licenseId" : null,
  "country" : "SIN",
  "name" : {
    "firstName" : "Tian Wei Jonathan",
    "lastName" : "AU EONG",
    "fullName" : "AU EONG, Tian Wei Jonathan"
  },
  "gender" : null,
  "hand" : null,
  "birthDay" : {
    "y" : 2000,
    "m" : 6,
    "d" : 6
  }
}, {
  "uid" : "32990",
  "licenseId" : null,
  "country" : "SIN",
  "name" : {
    "firstName" : "Nicole Xiao Xuan",
    "lastName" : "AW",
    "fullName" : "AW, Nicole Xiao Xuan"
  },
  "gender" : null,
  "hand" : null,
  "birthDay" : {
    "y" : 1997,
    "m" : 12,
    "d" : 5
  }
}, {
  "uid" : "32053",
  "licenseId" : null,
  "country" : "SIN",
  "name" : {
    "firstName" : "Aarya",
    "lastName" : "BERTHIER",
    "fullName" : "BERTHIER, Aarya"
  },
  "gender" : null,
  "hand" : null,
  "birthDay" : {
    "y" : 1999,
    "m" : 1,
    "d" : 11
  }
}, {
  "uid" : "33614",
  "licenseId" : null,
  "country" : "SIN",
  "name" : {
    "firstName" : "Amita",
    "lastName" : "BERTHIER",
    "fullName" : "BERTHIER, Amita"
  },
  "gender" : null,
  "hand" : null,
  "birthDay" : {
    "y" : 2000,
    "m" : 12,
    "d" : 15
  }
}, {
  "uid" : "11239",
  "licenseId" : null,
  "country" : "SIN",
  "name" : {
    "firstName" : "David Wei Ren",
    "lastName" : "CHAN",
    "fullName" : "CHAN, David Wei Ren"
  },
  "gender" : null,
  "hand" : null,
  "birthDay" : {
    "y" : 1984,
    "m" : 7,
    "d" : 12
  }
}, {
  "uid" : "31844",
  "licenseId" : null,
  "country" : "SIN",
  "name" : {
    "firstName" : "Kevin Jerrold",
    "lastName" : "CHAN",
    "fullName" : "CHAN, Kevin Jerrold"
  },
  "gender" : null,
  "hand" : null,
  "birthDay" : {
    "y" : 1998,
    "m" : 6,
    "d" : 19
  }
}, {
  "uid" : "28279",
  "licenseId" : null,
  "country" : "SIN",
  "name" : {
    "firstName" : "Wei Yu",
    "lastName" : "CHAN",
    "fullName" : "CHAN, Wei Yu"
  },
  "gender" : null,
  "hand" : null,
  "birthDay" : {
    "y" : 1996,
    "m" : 10,
    "d" : 5
  }
}, {
  "uid" : "33637",
  "licenseId" : null,
  "country" : "SIN",
  "name" : {
    "firstName" : "Xing Jian",
    "lastName" : "CHEN",
    "fullName" : "CHEN, Xing Jian"
  },
  "gender" : null,
  "hand" : null,
  "birthDay" : {
    "y" : 1998,
    "m" : 5,
    "d" : 4
  }
}, {
  "uid" : "32986",
  "licenseId" : null,
  "country" : "SIN",
  "name" : {
    "firstName" : "Zachary Yi",
    "lastName" : "CHEN",
    "fullName" : "CHEN, Zachary Yi"
  },
  "gender" : null,
  "hand" : null,
  "birthDay" : {
    "y" : 1998,
    "m" : 11,
    "d" : 10
  }
}, {
  "uid" : "36844",
  "licenseId" : null,
  "country" : "SIN",
  "name" : {
    "firstName" : "Jefferson Jia Hui",
    "lastName" : "CHEONG",
    "fullName" : "CHEONG, Jefferson Jia Hui"
  },
  "gender" : null,
  "hand" : null,
  "birthDay" : {
    "y" : 2000,
    "m" : 9,
    "d" : 30
  }
}, {
  "uid" : "29370",
  "licenseId" : null,
  "country" : "SIN",
  "name" : {
    "firstName" : "Sharmaine En-Qi",
    "lastName" : "CHEUNG",
    "fullName" : "CHEUNG, Sharmaine En-Qi"
  },
  "gender" : null,
  "hand" : null,
  "birthDay" : {
    "y" : 1992,
    "m" : 3,
    "d" : 17
  }
}, {
  "uid" : "31230",
  "licenseId" : null,
  "country" : "SIN",
  "name" : {
    "firstName" : "Yu Yong",
    "lastName" : "CHOY",
    "fullName" : "CHOY, Yu Yong"
  },
  "gender" : null,
  "hand" : null,
  "birthDay" : {
    "y" : 1997,
    "m" : 6,
    "d" : 18
  }
}, {
  "uid" : "35230",
  "licenseId" : null,
  "country" : "SIN",
  "name" : {
    "firstName" : "Fellini You Di",
    "lastName" : "ER",
    "fullName" : "ER, Fellini You Di"
  },
  "gender" : null,
  "hand" : null,
  "birthDay" : {
    "y" : 1999,
    "m" : 1,
    "d" : 9
  }
}, {
  "uid" : "36757",
  "licenseId" : null,
  "country" : "SIN",
  "name" : {
    "firstName" : "Zheng Jie",
    "lastName" : "FONG",
    "fullName" : "FONG, Zheng Jie"
  },
  "gender" : null,
  "hand" : null,
  "birthDay" : {
    "y" : 1999,
    "m" : 5,
    "d" : 7
  }
}, {
  "uid" : "35757",
  "licenseId" : null,
  "country" : "SIN",
  "name" : {
    "firstName" : "Nicole Li Shyan",
    "lastName" : "GOH",
    "fullName" : "GOH, Nicole Li Shyan"
  },
  "gender" : null,
  "hand" : null,
  "birthDay" : {
    "y" : 2000,
    "m" : 6,
    "d" : 9
  }
}, {
  "uid" : "27880",
  "licenseId" : null,
  "country" : "SIN",
  "name" : {
    "firstName" : "Wan Qi",
    "lastName" : "GOH",
    "fullName" : "GOH, Wan Qi"
  },
  "gender" : null,
  "hand" : null,
  "birthDay" : {
    "y" : 1990,
    "m" : 10,
    "d" : 25
  }
}, {
  "uid" : "39125",
  "licenseId" : null,
  "country" : "SIN",
  "name" : {
    "firstName" : "Yu Xiang Akira",
    "lastName" : "GOH",
    "fullName" : "GOH, Yu Xiang Akira"
  },
  "gender" : null,
  "hand" : null,
  "birthDay" : {
    "y" : 1999,
    "m" : 11,
    "d" : 18
  }
}, {
  "uid" : "11064",
  "licenseId" : null,
  "country" : "SIN",
  "name" : {
    "firstName" : "Magdalene Xin'en",
    "lastName" : "HUANG",
    "fullName" : "HUANG, Magdalene Xin'en"
  },
  "gender" : null,
  "hand" : null,
  "birthDay" : {
    "y" : 1983,
    "m" : 9,
    "d" : 26
  }
}, {
  "uid" : "39290",
  "licenseId" : null,
  "country" : "SIN",
  "name" : {
    "firstName" : "Jean Luc Cheng Kang",
    "lastName" : "HUN",
    "fullName" : "HUN, Jean Luc Cheng Kang"
  },
  "gender" : null,
  "hand" : null,
  "birthDay" : {
    "y" : 1998,
    "m" : 9,
    "d" : 5
  }
}, {
  "uid" : "39161",
  "licenseId" : null,
  "country" : "SIN",
  "name" : {
    "firstName" : "Yuan Chang",
    "lastName" : "IP",
    "fullName" : "IP, Yuan Chang"
  },
  "gender" : null,
  "hand" : null,
  "birthDay" : {
    "y" : 1994,
    "m" : 12,
    "d" : 1
  }
}, {
  "uid" : "33509",
  "licenseId" : null,
  "country" : "SIN",
  "name" : {
    "firstName" : "Esther Shi Ning",
    "lastName" : "LAI",
    "fullName" : "LAI, Esther Shi Ning"
  },
  "gender" : null,
  "hand" : null,
  "birthDay" : {
    "y" : 2000,
    "m" : 5,
    "d" : 3
  }
}, {
  "uid" : "34819",
  "licenseId" : null,
  "country" : "SIN",
  "name" : {
    "firstName" : "Jing Siang",
    "lastName" : "LAM",
    "fullName" : "LAM, Jing Siang"
  },
  "gender" : null,
  "hand" : null,
  "birthDay" : {
    "y" : 1999,
    "m" : 5,
    "d" : 28
  }
}, {
  "uid" : "30706",
  "licenseId" : null,
  "country" : "SIN",
  "name" : {
    "firstName" : "Ysien",
    "lastName" : "LAU",
    "fullName" : "LAU, Ysien"
  },
  "gender" : null,
  "hand" : null,
  "birthDay" : {
    "y" : 1998,
    "m" : 3,
    "d" : 27
  }
}, {
  "uid" : "34821",
  "licenseId" : null,
  "country" : "SIN",
  "name" : {
    "firstName" : "Ywen",
    "lastName" : "LAU",
    "fullName" : "LAU, Ywen"
  },
  "gender" : null,
  "hand" : null,
  "birthDay" : {
    "y" : 2000,
    "m" : 1,
    "d" : 24
  }
}, {
  "uid" : "18259",
  "licenseId" : null,
  "country" : "SIN",
  "name" : {
    "firstName" : "Ann Huimin",
    "lastName" : "LEE",
    "fullName" : "LEE, Ann Huimin"
  },
  "gender" : null,
  "hand" : null,
  "birthDay" : {
    "y" : 1991,
    "m" : 3,
    "d" : 13
  }
}, {
  "uid" : "36897",
  "licenseId" : null,
  "country" : "SIN",
  "name" : {
    "firstName" : "Bernardette Jing Fei",
    "lastName" : "LEE",
    "fullName" : "LEE, Bernardette Jing Fei"
  },
  "gender" : null,
  "hand" : null,
  "birthDay" : {
    "y" : 1988,
    "m" : 9,
    "d" : 16
  }
}, {
  "uid" : "31047",
  "licenseId" : null,
  "country" : "SIN",
  "name" : {
    "firstName" : "Candice Kar Hwei",
    "lastName" : "LEE",
    "fullName" : "LEE, Candice Kar Hwei"
  },
  "gender" : null,
  "hand" : null,
  "birthDay" : {
    "y" : 1997,
    "m" : 7,
    "d" : 24
  }
}, {
  "uid" : "32991",
  "licenseId" : null,
  "country" : "SIN",
  "name" : {
    "firstName" : "Jolie Kar Yi",
    "lastName" : "LEE",
    "fullName" : "LEE, Jolie Kar Yi"
  },
  "gender" : null,
  "hand" : null,
  "birthDay" : {
    "y" : 1998,
    "m" : 10,
    "d" : 27
  }
}, {
  "uid" : "18264",
  "licenseId" : null,
  "country" : "SIN",
  "name" : {
    "firstName" : "Samson Mun Hou",
    "lastName" : "LEE",
    "fullName" : "LEE, Samson Mun Hou"
  },
  "gender" : null,
  "hand" : null,
  "birthDay" : {
    "y" : 1986,
    "m" : 12,
    "d" : 11
  }
}, {
  "uid" : "31043",
  "licenseId" : null,
  "country" : "SIN",
  "name" : {
    "firstName" : "Samuel",
    "lastName" : "LEE",
    "fullName" : "LEE, Samuel"
  },
  "gender" : null,
  "hand" : null,
  "birthDay" : {
    "y" : 1997,
    "m" : 1,
    "d" : 27
  }
}, {
  "uid" : "29391",
  "licenseId" : null,
  "country" : "SIN",
  "name" : {
    "firstName" : "Clive Yi Yang",
    "lastName" : "LEU",
    "fullName" : "LEU, Clive Yi Yang"
  },
  "gender" : null,
  "hand" : null,
  "birthDay" : {
    "y" : 1994,
    "m" : 11,
    "d" : 10
  }
}, {
  "uid" : "22920",
  "licenseId" : null,
  "country" : "SIN",
  "name" : {
    "firstName" : "Cheryl",
    "lastName" : "LIM",
    "fullName" : "LIM, Cheryl"
  },
  "gender" : null,
  "hand" : null,
  "birthDay" : {
    "y" : 1993,
    "m" : 7,
    "d" : 8
  }
}, {
  "uid" : "33190",
  "licenseId" : null,
  "country" : "SIN",
  "name" : {
    "firstName" : "Elizabeth Ann Yu Yan",
    "lastName" : "LIM",
    "fullName" : "LIM, Elizabeth Ann Yu Yan"
  },
  "gender" : null,
  "hand" : null,
  "birthDay" : {
    "y" : 1994,
    "m" : 11,
    "d" : 8
  }
}, {
  "uid" : "29196",
  "licenseId" : null,
  "country" : "SIN",
  "name" : {
    "firstName" : "Joshua Ian",
    "lastName" : "LIM",
    "fullName" : "LIM, Joshua Ian"
  },
  "gender" : null,
  "hand" : null,
  "birthDay" : {
    "y" : 1996,
    "m" : 1,
    "d" : 12
  }
}, {
  "uid" : "33679",
  "licenseId" : null,
  "country" : "SIN",
  "name" : {
    "firstName" : "Justin Ren Hsien",
    "lastName" : "LIM",
    "fullName" : "LIM, Justin Ren Hsien"
  },
  "gender" : null,
  "hand" : null,
  "birthDay" : {
    "y" : 1998,
    "m" : 11,
    "d" : 9
  }
}, {
  "uid" : "33782",
  "licenseId" : null,
  "country" : "SIN",
  "name" : {
    "firstName" : "Neville Woon Juin",
    "lastName" : "LIM",
    "fullName" : "LIM, Neville Woon Juin"
  },
  "gender" : null,
  "hand" : null,
  "birthDay" : {
    "y" : 1998,
    "m" : 8,
    "d" : 31
  }
}, {
  "uid" : "22654",
  "licenseId" : null,
  "country" : "SIN",
  "name" : {
    "firstName" : "Victoria Ann Xiu Yan",
    "lastName" : "LIM",
    "fullName" : "LIM, Victoria Ann Xiu Yan"
  },
  "gender" : null,
  "hand" : null,
  "birthDay" : {
    "y" : 1989,
    "m" : 4,
    "d" : 20
  }
}, {
  "uid" : "21124",
  "licenseId" : null,
  "country" : "SIN",
  "name" : {
    "firstName" : "Wei Wen",
    "lastName" : "LIM",
    "fullName" : "LIM, Wei Wen"
  },
  "gender" : null,
  "hand" : null,
  "birthDay" : {
    "y" : 1985,
    "m" : 3,
    "d" : 4
  }
}, {
  "uid" : "37344",
  "licenseId" : null,
  "country" : "SIN",
  "name" : {
    "firstName" : "Ron Ken Yang",
    "lastName" : "LOH",
    "fullName" : "LOH, Ron Ken Yang"
  },
  "gender" : null,
  "hand" : null,
  "birthDay" : {
    "y" : 1999,
    "m" : 2,
    "d" : 19
  }
}, {
  "uid" : "35753",
  "licenseId" : null,
  "country" : "SIN",
  "name" : {
    "firstName" : "Wei Hao Nicholas",
    "lastName" : "LOO",
    "fullName" : "LOO, Wei Hao Nicholas"
  },
  "gender" : null,
  "hand" : null,
  "birthDay" : {
    "y" : 1999,
    "m" : 9,
    "d" : 14
  }
}, {
  "uid" : "35748",
  "licenseId" : null,
  "country" : "SIN",
  "name" : {
    "firstName" : "Alasdair Hoi Kit",
    "lastName" : "LOW",
    "fullName" : "LOW, Alasdair Hoi Kit"
  },
  "gender" : null,
  "hand" : null,
  "birthDay" : {
    "y" : 2000,
    "m" : 3,
    "d" : 1
  }
}, {
  "uid" : "35871",
  "licenseId" : null,
  "country" : "SIN",
  "name" : {
    "firstName" : "Grace",
    "lastName" : "MUN",
    "fullName" : "MUN, Grace"
  },
  "gender" : null,
  "hand" : null,
  "birthDay" : {
    "y" : 1999,
    "m" : 9,
    "d" : 13
  }
}, {
  "uid" : "28844",
  "licenseId" : null,
  "country" : "SIN",
  "name" : {
    "firstName" : "Jet Shang Fei",
    "lastName" : "NG",
    "fullName" : "NG, Jet Shang Fei"
  },
  "gender" : null,
  "hand" : null,
  "birthDay" : {
    "y" : 1998,
    "m" : 5,
    "d" : 10
  }
}, {
  "uid" : "39647",
  "licenseId" : null,
  "country" : "SIN",
  "name" : {
    "firstName" : "Jewel Xing Yee",
    "lastName" : "NG",
    "fullName" : "NG, Jewel Xing Yee"
  },
  "gender" : null,
  "hand" : null,
  "birthDay" : {
    "y" : 1998,
    "m" : 4,
    "d" : 30
  }
}, {
  "uid" : "34823",
  "licenseId" : null,
  "country" : "SIN",
  "name" : {
    "firstName" : "Joyce Mei Yi",
    "lastName" : "NG",
    "fullName" : "NG, Joyce Mei Yi"
  },
  "gender" : null,
  "hand" : null,
  "birthDay" : {
    "y" : 1998,
    "m" : 8,
    "d" : 5
  }
}, {
  "uid" : "35754",
  "licenseId" : null,
  "country" : "SIN",
  "name" : {
    "firstName" : "Jessica Shu Hui",
    "lastName" : "ONG",
    "fullName" : "ONG, Jessica Shu Hui"
  },
  "gender" : null,
  "hand" : null,
  "birthDay" : {
    "y" : 1999,
    "m" : 10,
    "d" : 28
  }
}, {
  "uid" : "27145",
  "licenseId" : null,
  "country" : "SIN",
  "name" : {
    "firstName" : "Justin Xian Shi",
    "lastName" : "ONG",
    "fullName" : "ONG, Justin Xian Shi"
  },
  "gender" : null,
  "hand" : null,
  "birthDay" : {
    "y" : 1994,
    "m" : 11,
    "d" : 8
  }
}, {
  "uid" : "35173",
  "licenseId" : null,
  "country" : "SIN",
  "name" : {
    "firstName" : "Ryan Ren An",
    "lastName" : "ONG",
    "fullName" : "ONG, Ryan Ren An"
  },
  "gender" : null,
  "hand" : null,
  "birthDay" : {
    "y" : 1999,
    "m" : 8,
    "d" : 29
  }
}, {
  "uid" : "27143",
  "licenseId" : null,
  "country" : "SIN",
  "name" : {
    "firstName" : "Rania Herlina",
    "lastName" : "RAHARDJA",
    "fullName" : "RAHARDJA, Rania Herlina"
  },
  "gender" : null,
  "hand" : null,
  "birthDay" : {
    "y" : 1993,
    "m" : 5,
    "d" : 15
  }
}, {
  "uid" : "37345",
  "licenseId" : null,
  "country" : "SIN",
  "name" : {
    "firstName" : "Daniel Rui En",
    "lastName" : "SEE",
    "fullName" : "SEE, Daniel Rui En"
  },
  "gender" : null,
  "hand" : null,
  "birthDay" : {
    "y" : 1999,
    "m" : 7,
    "d" : 18
  }
}, {
  "uid" : "39225",
  "licenseId" : null,
  "country" : "SIN",
  "name" : {
    "firstName" : "Darren Jun Hao",
    "lastName" : "TAN",
    "fullName" : "TAN, Darren Jun Hao"
  },
  "gender" : null,
  "hand" : null,
  "birthDay" : {
    "y" : 2000,
    "m" : 1,
    "d" : 21
  }
}, {
  "uid" : "32988",
  "licenseId" : null,
  "country" : "SIN",
  "name" : {
    "firstName" : "Jeremy Zheng Yi",
    "lastName" : "TAN",
    "fullName" : "TAN, Jeremy Zheng Yi"
  },
  "gender" : null,
  "hand" : null,
  "birthDay" : {
    "y" : 1997,
    "m" : 12,
    "d" : 19
  }
}, {
  "uid" : "40760",
  "licenseId" : null,
  "country" : "SIN",
  "name" : {
    "firstName" : "Veralyn Chou Xin",
    "lastName" : "TAN",
    "fullName" : "TAN, Veralyn Chou Xin"
  },
  "gender" : null,
  "hand" : null,
  "birthDay" : {
    "y" : 2001,
    "m" : 11,
    "d" : 4
  }
}, {
  "uid" : "37346",
  "licenseId" : null,
  "country" : "SIN",
  "name" : {
    "firstName" : "Weixuan",
    "lastName" : "TAN",
    "fullName" : "TAN, Weixuan"
  },
  "gender" : null,
  "hand" : null,
  "birthDay" : {
    "y" : 1998,
    "m" : 9,
    "d" : 21
  }
}, {
  "uid" : "32401",
  "licenseId" : null,
  "country" : "SIN",
  "name" : {
    "firstName" : "Lin Fang",
    "lastName" : "TSENG",
    "fullName" : "TSENG, Lin Fang"
  },
  "gender" : null,
  "hand" : null,
  "birthDay" : {
    "y" : 1983,
    "m" : 5,
    "d" : 4
  }
}, {
  "uid" : "10435",
  "licenseId" : null,
  "country" : "SIN",
  "name" : {
    "firstName" : "Wenying",
    "lastName" : "WANG",
    "fullName" : "WANG, Wenying"
  },
  "gender" : null,
  "hand" : null,
  "birthDay" : {
    "y" : 1980,
    "m" : 11,
    "d" : 24
  }
}, {
  "uid" : "15801",
  "licenseId" : null,
  "country" : "SIN",
  "name" : {
    "firstName" : "Cheryl Ye Han",
    "lastName" : "WONG",
    "fullName" : "WONG, Cheryl Ye Han"
  },
  "gender" : null,
  "hand" : null,
  "birthDay" : {
    "y" : 1991,
    "m" : 3,
    "d" : 8
  }
}, {
  "uid" : "36842",
  "licenseId" : null,
  "country" : "SIN",
  "name" : {
    "firstName" : "Joshua Chun Wei",
    "lastName" : "WONG",
    "fullName" : "WONG, Joshua Chun Wei"
  },
  "gender" : null,
  "hand" : null,
  "birthDay" : {
    "y" : 1998,
    "m" : 4,
    "d" : 6
  }
}, {
  "uid" : "22650",
  "licenseId" : null,
  "country" : "SIN",
  "name" : {
    "firstName" : "Liane Ye Ying",
    "lastName" : "WONG",
    "fullName" : "WONG, Liane Ye Ying"
  },
  "gender" : null,
  "hand" : null,
  "birthDay" : {
    "y" : 1994,
    "m" : 3,
    "d" : 23
  }
}, {
  "uid" : "33825",
  "licenseId" : null,
  "country" : "SIN",
  "name" : {
    "firstName" : "Maxine Jie Xin",
    "lastName" : "WONG",
    "fullName" : "WONG, Maxine Jie Xin"
  },
  "gender" : null,
  "hand" : null,
  "birthDay" : {
    "y" : 2001,
    "m" : 2,
    "d" : 3
  }
}, {
  "uid" : "31042",
  "licenseId" : null,
  "country" : "SIN",
  "name" : {
    "firstName" : "Nicole Mae Hui Shan",
    "lastName" : "WONG",
    "fullName" : "WONG, Nicole Mae Hui Shan"
  },
  "gender" : null,
  "hand" : null,
  "birthDay" : {
    "y" : 1998,
    "m" : 4,
    "d" : 26
  }
}, {
  "uid" : "33609",
  "licenseId" : null,
  "country" : "SIN",
  "name" : {
    "firstName" : "Tatiana Yu Rong",
    "lastName" : "WONG",
    "fullName" : "WONG, Tatiana Yu Rong"
  },
  "gender" : null,
  "hand" : null,
  "birthDay" : {
    "y" : 1999,
    "m" : 1,
    "d" : 16
  }
}, {
  "uid" : "35749",
  "licenseId" : null,
  "country" : "SIN",
  "name" : {
    "firstName" : "Jing Zhe",
    "lastName" : "YEO",
    "fullName" : "YEO, Jing Zhe"
  },
  "gender" : null,
  "hand" : null,
  "birthDay" : {
    "y" : 2000,
    "m" : 9,
    "d" : 16
  }
}, {
  "uid" : "41235",
  "licenseId" : null,
  "country" : "SIN",
  "name" : {
    "firstName" : "Ryan Yuan Zhen",
    "lastName" : "YEO",
    "fullName" : "YEO, Ryan Yuan Zhen"
  },
  "gender" : null,
  "hand" : null,
  "birthDay" : {
    "y" : 2000,
    "m" : 7,
    "d" : 19
  }
}, {
  "uid" : "36105",
  "licenseId" : null,
  "country" : "SIN",
  "name" : {
    "firstName" : "Mei Xin Christabel",
    "lastName" : "YONG",
    "fullName" : "YONG, Mei Xin Christabel"
  },
  "gender" : null,
  "hand" : null,
  "birthDay" : {
    "y" : 1995,
    "m" : 1,
    "d" : 17
  }
} ]